{"@timestamp":"2026-01-12T09:31:59.6633649+05:30","@version":"1","message":"STORAGE_INITIALIZED | baseDir=C:\\Users\\UMAR\\IdeaProjects\\billing-engine\\data","logger_name":"REQUEST_LOG","thread_name":"main","level":"INFO","level_value":20000,"event.domain":"billing","log.category":"app.storage"}
{"@timestamp":"2026-01-12T09:32:08.7135282+05:30","@version":"1","message":"REQUEST_RECEIVED | endpoint=POST /bill/process | account=ACC777 | inputFormat=JSON | outputFormat=XML | payload=BillInput(header=BillInput.Header(accountNo=ACC777, issueDate=12/16/2025, jurisdiction=NYC, previousBalance=null, servicePoints=[BillInput.ServicePoint(id=null, type=null, meters=[BillInput.Meter(id=null, readings=[BillInput.Reading(period=null, usageKwh=500.0, rateTier=TIER1)])])]))","logger_name":"REQUEST_LOG","thread_name":"main","level":"INFO","level_value":20000,"log.type":"process.request","event.domain":"billing"}
{"@timestamp":"2026-01-12T09:32:08.7579221+05:30","@version":"1","message":"PROCESS_START | account=ACC777 | inputFormat=JSON | outputFormat=XML","logger_name":"REQUEST_LOG","thread_name":"main","level":"INFO","level_value":20000,"event.domain":"billing","log.category":"process.start"}
{"@timestamp":"2026-01-12T09:32:08.7973727+05:30","@version":"1","message":"INPUT_STORED | file=ACC777_20260112093208_IN.json | format=JSON","logger_name":"REQUEST_LOG","thread_name":"main","level":"INFO","level_value":20000,"event.domain":"billing","log.category":"data.input"}
{"@timestamp":"2026-01-12T09:32:11.0022525+05:30","@version":"1","message":"STORAGE_INITIALIZED | baseDir=C:\\Users\\UMAR\\IdeaProjects\\billing-engine\\data","logger_name":"REQUEST_LOG","thread_name":"main","level":"INFO","level_value":20000,"event.domain":"billing","log.category":"app.storage"}
{"@timestamp":"2026-01-12T09:32:12.1073415+05:30","@version":"1","message":"PROCESS_START | account=ACC999 | inputFormat=XML | outputFormat=JSON","logger_name":"REQUEST_LOG","thread_name":"main","level":"INFO","level_value":20000,"event.domain":"billing","log.category":"process.start"}
{"@timestamp":"2026-01-12T09:32:12.1442884+05:30","@version":"1","message":"INPUT_STORED | file=ACC999_20260112093212_IN.xml | format=XML","logger_name":"REQUEST_LOG","thread_name":"main","level":"INFO","level_value":20000,"event.domain":"billing","log.category":"data.input"}
{"@timestamp":"2026-01-12T09:32:12.1527797+05:30","@version":"1","message":"PROCESSING_SKIPPED | gate=DISABLED | movedToReplay=ACC999_20260112093212_IN.xml","logger_name":"REQUEST_LOG","thread_name":"main","level":"WARN","level_value":30000,"event.domain":"billing","log.category":"process.skipped"}
{"@timestamp":"2026-01-12T09:32:12.4044864+05:30","@version":"1","message":"REPLAY_START | account=ACC123 | file=ACC123_20260107103815_IN.xml","logger_name":"REQUEST_LOG","thread_name":"main","level":"INFO","level_value":20000,"event.domain":"billing","log.category":"replay.start"}
{"@timestamp":"2026-01-12T09:32:12.5000409+05:30","@version":"1","message":"REPLAY_START | account=ACC999 | file=ACC999_20260112093212_IN.xml","logger_name":"REQUEST_LOG","thread_name":"main","level":"INFO","level_value":20000,"event.domain":"billing","log.category":"replay.start"}
{"@timestamp":"2026-01-12T09:32:12.6948292+05:30","@version":"1","message":"PROCESS_START | account=ACC123 | inputFormat=XML | outputFormat=JSON","logger_name":"REQUEST_LOG","thread_name":"main","level":"INFO","level_value":20000,"event.domain":"billing","log.category":"process.start"}
{"@timestamp":"2026-01-12T09:32:12.7005156+05:30","@version":"1","message":"INPUT_STORED | file=ACC123_20260112093212_IN.xml | format=XML","logger_name":"REQUEST_LOG","thread_name":"main","level":"INFO","level_value":20000,"event.domain":"billing","log.category":"data.input"}
{"@timestamp":"2026-01-12T09:32:12.750052+05:30","@version":"1","message":"PROCESS_START | account=ACC123 | inputFormat=XML | outputFormat=JSON","logger_name":"REQUEST_LOG","thread_name":"main","level":"INFO","level_value":20000,"event.domain":"billing","log.category":"process.start"}
{"@timestamp":"2026-01-12T09:32:12.7572816+05:30","@version":"1","message":"INPUT_STORED | file=ACC123_20260112093212_IN.xml | format=XML","logger_name":"REQUEST_LOG","thread_name":"main","level":"INFO","level_value":20000,"event.domain":"billing","log.category":"data.input"}
{"@timestamp":"2026-01-12T09:32:12.7616513+05:30","@version":"1","message":"PROCESSING_SKIPPED | gate=DISABLED | movedToReplay=ACC123_20260112093212_IN.xml","logger_name":"REQUEST_LOG","thread_name":"main","level":"WARN","level_value":30000,"event.domain":"billing","log.category":"process.skipped"}
{"@timestamp":"2026-01-12T09:32:34.7265436+05:30","@version":"1","message":"STORAGE_INITIALIZED | baseDir=C:\\Users\\UMAR\\IdeaProjects\\billing-engine\\data","logger_name":"REQUEST_LOG","thread_name":"main","level":"INFO","level_value":20000,"event.domain":"billing","log.category":"app.storage"}
{"@timestamp":"2026-01-12T09:33:06.4871173+05:30","@version":"1","message":"REPLAY_START | account=ACC123 | file=ACC123_20260112093212_IN.xml","logger_name":"REQUEST_LOG","thread_name":"scheduling-1","level":"INFO","level_value":20000,"trace_id":"044b75e80527e50d85e84a182d9b3bad","event.domain":"billing","trace_flags":"01","span_id":"f35a2373ca9757dc","log.category":"replay.start"}
{"@timestamp":"2026-01-12T09:40:43.1373975+05:30","@version":"1","message":"STORAGE_INITIALIZED | baseDir=C:\\Users\\UMAR\\IdeaProjects\\billing-engine\\data","logger_name":"REQUEST_LOG","thread_name":"main","level":"INFO","level_value":20000,"event.domain":"billing","log.category":"app.storage"}
{"@timestamp":"2026-01-12T09:46:12.3696609+05:30","@version":"1","message":"STORAGE_INITIALIZED | baseDir=C:\\Users\\UMAR\\IdeaProjects\\billing-engine\\data","logger_name":"REQUEST_LOG","thread_name":"main","level":"INFO","level_value":20000,"event.domain":"billing","log.category":"app.storage"}
{"@timestamp":"2026-01-12T09:52:32.1335963+05:30","@version":"1","message":"STORAGE_INITIALIZED | baseDir=C:\\Users\\UMAR\\IdeaProjects\\billing-engine\\data","logger_name":"REQUEST_LOG","thread_name":"main","level":"INFO","level_value":20000,"event.domain":"billing","log.category":"app.storage"}
{"@timestamp":"2026-01-12T09:52:51.8904605+05:30","@version":"1","message":"REQUEST_RECEIVED | endpoint=POST /bill/process | account=ACC-UPSTATE-101 | inputFormat=XML | outputFormat=JSON | payload=BillInput(header=BillInput.Header(accountNo=ACC-UPSTATE-101, issueDate=12/31/2025, jurisdiction=ALBANY, previousBalance=null, servicePoints=[BillInput.ServicePoint(id=SP01, type=null, meters=[BillInput.Meter(id=M3, readings=[BillInput.Reading(period=null, usageKwh=1000.0, rateTier=TIER2)])])]))","logger_name":"REQUEST_LOG","thread_name":"http-nio-8080-exec-2","level":"INFO","level_value":20000,"log.type":"process.request","event.domain":"billing"}
{"@timestamp":"2026-01-12T09:52:51.8986026+05:30","@version":"1","message":"PROCESS_START | account=ACC-UPSTATE-101 | inputFormat=XML | outputFormat=JSON","logger_name":"REQUEST_LOG","thread_name":"http-nio-8080-exec-2","level":"INFO","level_value":20000,"event.domain":"billing","log.category":"process.start"}
{"@timestamp":"2026-01-12T09:52:52.0636088+05:30","@version":"1","message":"INPUT_STORED | file=ACC-UPSTATE-101_20260112095251_IN.xml | format=XML","logger_name":"REQUEST_LOG","thread_name":"http-nio-8080-exec-2","level":"INFO","level_value":20000,"event.domain":"billing","log.category":"data.input"}
{"@timestamp":"2026-01-12T09:53:03.8678802+05:30","@version":"1","message":"REQUEST_RECEIVED | endpoint=POST /bill/process | account=ACC-UPSTATE-101 | inputFormat=XML | outputFormat=JSON | payload=BillInput(header=BillInput.Header(accountNo=ACC-UPSTATE-101, issueDate=12/31/2025, jurisdiction=ALBANY, previousBalance=null, servicePoints=[BillInput.ServicePoint(id=SP01, type=null, meters=[BillInput.Meter(id=M3, readings=[BillInput.Reading(period=null, usageKwh=1000.0, rateTier=TIER2)])])]))","logger_name":"REQUEST_LOG","thread_name":"http-nio-8080-exec-3","level":"INFO","level_value":20000,"log.type":"process.request","event.domain":"billing"}
{"@timestamp":"2026-01-12T09:53:03.8761123+05:30","@version":"1","message":"PROCESS_START | account=ACC-UPSTATE-101 | inputFormat=XML | outputFormat=JSON","logger_name":"REQUEST_LOG","thread_name":"http-nio-8080-exec-3","level":"INFO","level_value":20000,"event.domain":"billing","log.category":"process.start"}
{"@timestamp":"2026-01-12T09:53:03.8816933+05:30","@version":"1","message":"INPUT_STORED | file=ACC-UPSTATE-101_20260112095303_IN.xml | format=XML","logger_name":"REQUEST_LOG","thread_name":"http-nio-8080-exec-3","level":"INFO","level_value":20000,"event.domain":"billing","log.category":"data.input"}
{"@timestamp":"2026-01-12T09:53:05.510377+05:30","@version":"1","message":"REQUEST_RECEIVED | endpoint=POST /bill/process | account=ACC-UPSTATE-101 | inputFormat=XML | outputFormat=JSON | payload=BillInput(header=BillInput.Header(accountNo=ACC-UPSTATE-101, issueDate=12/31/2025, jurisdiction=ALBANY, previousBalance=null, servicePoints=[BillInput.ServicePoint(id=SP01, type=null, meters=[BillInput.Meter(id=M3, readings=[BillInput.Reading(period=null, usageKwh=1000.0, rateTier=TIER2)])])]))","logger_name":"REQUEST_LOG","thread_name":"http-nio-8080-exec-4","level":"INFO","level_value":20000,"log.type":"process.request","event.domain":"billing"}
{"@timestamp":"2026-01-12T09:53:05.510377+05:30","@version":"1","message":"PROCESS_START | account=ACC-UPSTATE-101 | inputFormat=XML | outputFormat=JSON","logger_name":"REQUEST_LOG","thread_name":"http-nio-8080-exec-4","level":"INFO","level_value":20000,"event.domain":"billing","log.category":"process.start"}
{"@timestamp":"2026-01-12T09:53:05.5156175+05:30","@version":"1","message":"INPUT_STORED | file=ACC-UPSTATE-101_20260112095305_IN.xml | format=XML","logger_name":"REQUEST_LOG","thread_name":"http-nio-8080-exec-4","level":"INFO","level_value":20000,"event.domain":"billing","log.category":"data.input"}
{"@timestamp":"2026-01-12T10:01:11.6034513+05:30","@version":"1","message":"STORAGE_INITIALIZED | baseDir=C:\\Users\\UMAR\\IdeaProjects\\billing-engine\\data","logger_name":"REQUEST_LOG","thread_name":"main","level":"INFO","level_value":20000,"event.domain":"billing","log.category":"app.storage"}
{"@timestamp":"2026-01-12T10:05:08.7590891+05:30","@version":"1","message":"STORAGE_INITIALIZED | baseDir=C:\\Users\\UMAR\\IdeaProjects\\billing-engine\\data","logger_name":"REQUEST_LOG","thread_name":"main","level":"INFO","level_value":20000,"event.domain":"billing","log.category9":"app.storage"}
{"@timestamp":"2026-01-12T10:05:14.8006098+05:30","@version":"1","message":"REQUEST_RECEIVED | endpoint=POST /bill/process | account=ACC777 | inputFormat=JSON | outputFormat=XML | payload=BillInput(header=BillInput.Header(accountNo=ACC777, issueDate=12/16/2025, jurisdiction=NYC, previousBalance=null, servicePoints=[BillInput.ServicePoint(id=null, type=null, meters=[BillInput.Meter(id=null, readings=[BillInput.Reading(period=null, usageKwh=500.0, rateTier=TIER1)])])]))","logger_name":"REQUEST_LOG","thread_name":"main","level":"INFO","level_value":20000,"log.type":"process.request","event.domain":"billing"}
{"@timestamp":"2026-01-12T10:05:14.8487149+05:30","@version":"1","message":"PROCESS_START | account=ACC777 | inputFormat=JSON | outputFormat=XML","logger_name":"REQUEST_LOG","thread_name":"main","level":"INFO","level_value":20000,"event.domain":"billing","log.category9":"process.start"}
{"@timestamp":"2026-01-12T10:05:14.882677+05:30","@version":"1","message":"INPUT_STORED | file=ACC777_20260112100514_IN.json | format=JSON","logger_name":"REQUEST_LOG","thread_name":"main","level":"INFO","level_value":20000,"event.domain":"billing","log.category9":"data.input"}
{"@timestamp":"2026-01-12T10:05:16.4879588+05:30","@version":"1","message":"STORAGE_INITIALIZED | baseDir=C:\\Users\\UMAR\\IdeaProjects\\billing-engine\\data","logger_name":"REQUEST_LOG","thread_name":"main","level":"INFO","level_value":20000,"event.domain":"billing","log.category9":"app.storage"}
{"@timestamp":"2026-01-12T10:05:17.1407726+05:30","@version":"1","message":"PROCESS_START | account=ACC999 | inputFormat=XML | outputFormat=JSON","logger_name":"REQUEST_LOG","thread_name":"main","level":"INFO","level_value":20000,"event.domain":"billing","log.category9":"process.start"}
{"@timestamp":"2026-01-12T10:05:17.1629849+05:30","@version":"1","message":"INPUT_STORED | file=ACC999_20260112100517_IN.xml | format=XML","logger_name":"REQUEST_LOG","thread_name":"main","level":"INFO","level_value":20000,"event.domain":"billing","log.category9":"data.input"}
{"@timestamp":"2026-01-12T10:05:17.1629849+05:30","@version":"1","message":"PROCESSING_SKIPPED | gate=DISABLED | movedToReplay=ACC999_20260112100517_IN.xml","logger_name":"REQUEST_LOG","thread_name":"main","level":"WARN","level_value":30000,"event.domain":"billing","log.category9":"process.skipped"}
{"@timestamp":"2026-01-12T10:05:17.3372678+05:30","@version":"1","message":"REPLAY_START | account=ACC999 | file=ACC999_20260112100517_IN.xml","logger_name":"REQUEST_LOG","thread_name":"main","level":"INFO","level_value":20000,"event.domain":"billing","log.category9":"replay.start"}
{"@timestamp":"2026-01-12T10:05:17.5249109+05:30","@version":"1","message":"PROCESS_START | account=ACC123 | inputFormat=XML | outputFormat=JSON","logger_name":"REQUEST_LOG","thread_name":"main","level":"INFO","level_value":20000,"event.domain":"billing","log.category9":"process.start"}
{"@timestamp":"2026-01-12T10:05:17.5327569+05:30","@version":"1","message":"INPUT_STORED | file=ACC123_20260112100517_IN.xml | format=XML","logger_name":"REQUEST_LOG","thread_name":"main","level":"INFO","level_value":20000,"event.domain":"billing","log.category9":"data.input"}
{"@timestamp":"2026-01-12T10:05:17.5937405+05:30","@version":"1","message":"PROCESS_START | account=ACC123 | inputFormat=XML | outputFormat=JSON","logger_name":"REQUEST_LOG","thread_name":"main","level":"INFO","level_value":20000,"event.domain":"billing","log.category9":"process.start"}
{"@timestamp":"2026-01-12T10:05:17.5998167+05:30","@version":"1","message":"INPUT_STORED | file=ACC123_20260112100517_IN.xml | format=XML","logger_name":"REQUEST_LOG","thread_name":"main","level":"INFO","level_value":20000,"event.domain":"billing","log.category9":"data.input"}
{"@timestamp":"2026-01-12T10:05:17.6055219+05:30","@version":"1","message":"PROCESSING_SKIPPED | gate=DISABLED | movedToReplay=ACC123_20260112100517_IN.xml","logger_name":"REQUEST_LOG","thread_name":"main","level":"WARN","level_value":30000,"event.domain":"billing","log.category9":"process.skipped"}
{"@timestamp":"2026-01-12T10:06:29.1287428+05:30","@version":"1","message":"STORAGE_INITIALIZED | baseDir=C:\\Users\\UMAR\\IdeaProjects\\billing-engine\\data","logger_name":"REQUEST_LOG","thread_name":"main","level":"INFO","level_value":20000,"event.domain":"billing","log.category9":"app.storage"}
{"@timestamp":"2026-01-12T10:07:00.9280441+05:30","@version":"1","message":"REPLAY_START | account=ACC123 | file=ACC123_20260112100517_IN.xml","logger_name":"REQUEST_LOG","thread_name":"scheduling-1","level":"INFO","level_value":20000,"log.category9":"replay.start","trace_id":"ed5e1e6ff34c928d69ce8ab2d66a9c63","event.domain":"billing","trace_flags":"01","span_id":"0971877804873798"}
{"@timestamp":"2026-01-12T10:07:14.2177765+05:30","@version":"1","message":"REQUEST_RECEIVED | endpoint=POST /bill/process | account=ACC-UPSTATE-101 | inputFormat=XML | outputFormat=JSON | payload=BillInput(header=BillInput.Header(accountNo=ACC-UPSTATE-101, issueDate=12/31/2025, jurisdiction=ALBANY, previousBalance=null, servicePoints=[BillInput.ServicePoint(id=SP01, type=null, meters=[BillInput.Meter(id=M3, readings=[BillInput.Reading(period=null, usageKwh=1000.0, rateTier=TIER2)])])]))","logger_name":"REQUEST_LOG","thread_name":"http-nio-8080-exec-1","level":"INFO","level_value":20000,"log.type":"process.request","trace_id":"e87e05d4276f548789007ea532818738","event.domain":"billing","trace_flags":"01","span_id":"7dff013cb7d3a614"}
{"@timestamp":"2026-01-12T10:07:14.2341911+05:30","@version":"1","message":"PROCESS_START | account=ACC-UPSTATE-101 | inputFormat=XML | outputFormat=JSON","logger_name":"REQUEST_LOG","thread_name":"http-nio-8080-exec-1","level":"INFO","level_value":20000,"log.category9":"process.start","trace_id":"e87e05d4276f548789007ea532818738","event.domain":"billing","trace_flags":"01","span_id":"7dff013cb7d3a614"}
{"@timestamp":"2026-01-12T10:07:14.2831123+05:30","@version":"1","message":"INPUT_STORED | file=ACC-UPSTATE-101_20260112100714_IN.xml | format=XML","logger_name":"REQUEST_LOG","thread_name":"http-nio-8080-exec-1","level":"INFO","level_value":20000,"log.category9":"data.input","trace_id":"e87e05d4276f548789007ea532818738","event.domain":"billing","trace_flags":"01","span_id":"7dff013cb7d3a614"}
