{"@timestamp":"2026-01-07T05:01:43.1722636+05:30","@version":"1","message":"OUTPUT_STORED | file=ACC777_20260107050143_OUT.xml | path=C:\\Users\\UMAR\\IdeaProjects\\billing-engine\\data\\success\\output\\ACC777_20260107050143_OUT.xml | format=XML","logger_name":"SUCCESS_LOG","thread_name":"main","level":"INFO","level_value":20000,"event.domain":"billing","log.category":"data.output"}
{"@timestamp":"2026-01-07T05:01:43.1770003+05:30","@version":"1","message":"PROCESSING_SUCCESS | account=ACC777 | totalDue=28.44","logger_name":"SUCCESS_LOG","thread_name":"main","level":"INFO","level_value":20000,"event.domain":"billing","log.category":"process.success"}
{"@timestamp":"2026-01-07T05:01:43.8190353+05:30","@version":"1","message":"OUTPUT_STORED | file=ACC999_OUT.xml | path=C:\\Users\\UMAR\\IdeaProjects\\billing-engine\\data\\success\\output\\ACC999_OUT.xml | format=XML","logger_name":"SUCCESS_LOG","thread_name":"main","level":"INFO","level_value":20000,"event.domain":"billing","log.category":"data.output"}
{"@timestamp":"2026-01-07T05:01:43.8230247+05:30","@version":"1","message":"REPLAY_SUCCESS | account=ACC999 | file=ACC999_20260107050143_IN.xml","logger_name":"SUCCESS_LOG","thread_name":"main","level":"INFO","level_value":20000,"event.domain":"billing","log.category":"replay.success"}
{"@timestamp":"2026-01-07T05:01:43.8901213+05:30","@version":"1","message":"OUTPUT_STORED | file=ACC123_20260107050143_OUT.json | path=C:\\Users\\UMAR\\IdeaProjects\\billing-engine\\data\\success\\output\\ACC123_20260107050143_OUT.json | format=JSON","logger_name":"SUCCESS_LOG","thread_name":"main","level":"INFO","level_value":20000,"event.domain":"billing","log.category":"data.output"}
{"@timestamp":"2026-01-07T05:01:43.893125+05:30","@version":"1","message":"PROCESSING_SUCCESS | account=ACC123 | totalDue=36.40","logger_name":"SUCCESS_LOG","thread_name":"main","level":"INFO","level_value":20000,"event.domain":"billing","log.category":"process.success"}
{"@timestamp":"2026-01-07T05:02:53.485056+05:30","@version":"1","message":"OUTPUT_STORED | file=ACC123_OUT.xml | path=C:\\Users\\UMAR\\IdeaProjects\\billing-engine\\data\\success\\output\\ACC123_OUT.xml | format=XML","logger_name":"SUCCESS_LOG","thread_name":"scheduling-1","level":"INFO","level_value":20000,"trace_id":"5582a452954c20bc115e5c04cc867f6e","event.domain":"billing","trace_flags":"01","span_id":"f2435cbee484fd7d","log.category":"data.output"}
{"@timestamp":"2026-01-07T05:02:53.493273+05:30","@version":"1","message":"REPLAY_SUCCESS | account=ACC123 | file=ACC123_20260107050143_IN.xml","logger_name":"SUCCESS_LOG","thread_name":"scheduling-1","level":"INFO","level_value":20000,"trace_id":"5582a452954c20bc115e5c04cc867f6e","event.domain":"billing","trace_flags":"01","span_id":"f2435cbee484fd7d","log.category":"replay.success"}
{"@timestamp":"2026-01-07T05:04:31.3408288+05:30","@version":"1","message":"OUTPUT_STORED | file=ACC-UPSTATE-101_20260107050431_OUT.json | path=C:\\Users\\UMAR\\IdeaProjects\\billing-engine\\data\\success\\output\\ACC-UPSTATE-101_20260107050431_OUT.json | format=JSON","logger_name":"SUCCESS_LOG","thread_name":"http-nio-8080-exec-2","level":"INFO","level_value":20000,"trace_id":"326520390a711ed61ed481e653c8c5aa","event.domain":"billing","trace_flags":"01","span_id":"d76e1707682294d1","log.category":"data.output"}
{"@timestamp":"2026-01-07T05:04:31.3438098+05:30","@version":"1","message":"PROCESSING_SUCCESS | account=ACC-UPSTATE-101 | totalDue=65.56","logger_name":"SUCCESS_LOG","thread_name":"http-nio-8080-exec-2","level":"INFO","level_value":20000,"trace_id":"326520390a711ed61ed481e653c8c5aa","event.domain":"billing","trace_flags":"01","span_id":"d76e1707682294d1","log.category":"process.success"}
{"@timestamp":"2026-01-07T05:04:32.5526403+05:30","@version":"1","message":"OUTPUT_STORED | file=ACC-UPSTATE-101_20260107050432_OUT.json | path=C:\\Users\\UMAR\\IdeaProjects\\billing-engine\\data\\success\\output\\ACC-UPSTATE-101_20260107050432_OUT.json | format=JSON","logger_name":"SUCCESS_LOG","thread_name":"http-nio-8080-exec-3","level":"INFO","level_value":20000,"trace_id":"35b6d63a2066b4ec90092fb2194ae384","event.domain":"billing","trace_flags":"01","span_id":"33e6d2847a22b297","log.category":"data.output"}
{"@timestamp":"2026-01-07T05:04:32.5596345+05:30","@version":"1","message":"PROCESSING_SUCCESS | account=ACC-UPSTATE-101 | totalDue=65.56","logger_name":"SUCCESS_LOG","thread_name":"http-nio-8080-exec-3","level":"INFO","level_value":20000,"trace_id":"35b6d63a2066b4ec90092fb2194ae384","event.domain":"billing","trace_flags":"01","span_id":"33e6d2847a22b297","log.category":"process.success"}
{"@timestamp":"2026-01-07T05:04:33.6361977+05:30","@version":"1","message":"OUTPUT_STORED | file=ACC-UPSTATE-101_20260107050433_OUT.json | path=C:\\Users\\UMAR\\IdeaProjects\\billing-engine\\data\\success\\output\\ACC-UPSTATE-101_20260107050433_OUT.json | format=JSON","logger_name":"SUCCESS_LOG","thread_name":"http-nio-8080-exec-4","level":"INFO","level_value":20000,"trace_id":"f4eedef108d68314aa368a9729e6a253","event.domain":"billing","trace_flags":"01","span_id":"201a13bea7acdaf5","log.category":"data.output"}
{"@timestamp":"2026-01-07T05:04:33.6391988+05:30","@version":"1","message":"PROCESSING_SUCCESS | account=ACC-UPSTATE-101 | totalDue=65.56","logger_name":"SUCCESS_LOG","thread_name":"http-nio-8080-exec-4","level":"INFO","level_value":20000,"trace_id":"f4eedef108d68314aa368a9729e6a253","event.domain":"billing","trace_flags":"01","span_id":"201a13bea7acdaf5","log.category":"process.success"}
{"@timestamp":"2026-01-07T05:05:02.641133+05:30","@version":"1","message":"OUTPUT_STORED | file=ACC-UPSTATE-101_20260107050502_OUT.json | path=C:\\Users\\UMAR\\IdeaProjects\\billing-engine\\data\\success\\output\\ACC-UPSTATE-101_20260107050502_OUT.json | format=JSON","logger_name":"SUCCESS_LOG","thread_name":"http-nio-8080-exec-10","level":"INFO","level_value":20000,"trace_id":"b1e6120c3c59099d210f75be94bf1224","event.domain":"billing","trace_flags":"01","span_id":"6bd0ba85c01e435b","log.category":"data.output"}
{"@timestamp":"2026-01-07T05:05:02.6454582+05:30","@version":"1","message":"PROCESSING_SUCCESS | account=ACC-UPSTATE-101 | totalDue=65.56","logger_name":"SUCCESS_LOG","thread_name":"http-nio-8080-exec-10","level":"INFO","level_value":20000,"trace_id":"b1e6120c3c59099d210f75be94bf1224","event.domain":"billing","trace_flags":"01","span_id":"6bd0ba85c01e435b","log.category":"process.success"}
{"@timestamp":"2026-01-07T05:05:53.5330929+05:30","@version":"1","message":"OUTPUT_STORED | file=ACC-UPSTATE-101_OUT.xml | path=C:\\Users\\UMAR\\IdeaProjects\\billing-engine\\data\\success\\output\\ACC-UPSTATE-101_OUT.xml | format=XML","logger_name":"SUCCESS_LOG","thread_name":"scheduling-1","level":"INFO","level_value":20000,"trace_id":"5ccfd2d811c10961ccb38328b768e88b","event.domain":"billing","trace_flags":"01","span_id":"0c202e54fd0b833f","log.category":"data.output"}
{"@timestamp":"2026-01-07T05:05:53.5397314+05:30","@version":"1","message":"REPLAY_SUCCESS | account=ACC-UPSTATE-101 | file=ACC-UPSTATE-101_20260107050446_IN.xml","logger_name":"SUCCESS_LOG","thread_name":"scheduling-1","level":"INFO","level_value":20000,"trace_id":"5ccfd2d811c10961ccb38328b768e88b","event.domain":"billing","trace_flags":"01","span_id":"0c202e54fd0b833f","log.category":"replay.success"}
{"@timestamp":"2026-01-07T05:05:53.5561875+05:30","@version":"1","message":"OUTPUT_STORED | file=ACC-UPSTATE-101_OUT.xml | path=C:\\Users\\UMAR\\IdeaProjects\\billing-engine\\data\\success\\output\\ACC-UPSTATE-101_OUT.xml | format=XML","logger_name":"SUCCESS_LOG","thread_name":"scheduling-1","level":"INFO","level_value":20000,"trace_id":"5ccfd2d811c10961ccb38328b768e88b","event.domain":"billing","trace_flags":"01","span_id":"0c202e54fd0b833f","log.category":"data.output"}
{"@timestamp":"2026-01-07T05:05:53.5639518+05:30","@version":"1","message":"REPLAY_SUCCESS | account=ACC-UPSTATE-101 | file=ACC-UPSTATE-101_20260107050448_IN.xml","logger_name":"SUCCESS_LOG","thread_name":"scheduling-1","level":"INFO","level_value":20000,"trace_id":"5ccfd2d811c10961ccb38328b768e88b","event.domain":"billing","trace_flags":"01","span_id":"0c202e54fd0b833f","log.category":"replay.success"}
{"@timestamp":"2026-01-07T05:15:21.7150017+05:30","@version":"1","message":"OUTPUT_STORED | file=ACC-UPSTATE-101_20260107051521_OUT.json | path=C:\\Users\\UMAR\\IdeaProjects\\billing-engine\\data\\success\\output\\ACC-UPSTATE-101_20260107051521_OUT.json | format=JSON","logger_name":"SUCCESS_LOG","thread_name":"http-nio-8080-exec-1","level":"INFO","level_value":20000,"trace_id":"368e9ef3879f6eb84a053df274559f2d","event.domain":"billing","trace_flags":"01","span_id":"1cd7db2c7ef13d46","log.category":"data.output"}
{"@timestamp":"2026-01-07T05:15:21.7242942+05:30","@version":"1","message":"PROCESSING_SUCCESS | account=ACC-UPSTATE-101 | totalDue=65.56","logger_name":"SUCCESS_LOG","thread_name":"http-nio-8080-exec-1","level":"INFO","level_value":20000,"trace_id":"368e9ef3879f6eb84a053df274559f2d","event.domain":"billing","trace_flags":"01","span_id":"1cd7db2c7ef13d46","log.category":"process.success"}
{"@timestamp":"2026-01-07T05:15:26.4991834+05:30","@version":"1","message":"OUTPUT_STORED | file=ACC-UPSTATE-101_20260107051526_OUT.json | path=C:\\Users\\UMAR\\IdeaProjects\\billing-engine\\data\\success\\output\\ACC-UPSTATE-101_20260107051526_OUT.json | format=JSON","logger_name":"SUCCESS_LOG","thread_name":"http-nio-8080-exec-3","level":"INFO","level_value":20000,"trace_id":"9019314cc316699578bd2de0abaf05e0","event.domain":"billing","trace_flags":"01","span_id":"432cbe82ac632c3a","log.category":"data.output"}
{"@timestamp":"2026-01-07T05:15:26.5036793+05:30","@version":"1","message":"PROCESSING_SUCCESS | account=ACC-UPSTATE-101 | totalDue=65.56","logger_name":"SUCCESS_LOG","thread_name":"http-nio-8080-exec-3","level":"INFO","level_value":20000,"trace_id":"9019314cc316699578bd2de0abaf05e0","event.domain":"billing","trace_flags":"01","span_id":"432cbe82ac632c3a","log.category":"process.success"}
{"@timestamp":"2026-01-07T05:15:27.7534362+05:30","@version":"1","message":"OUTPUT_STORED | file=ACC-UPSTATE-101_20260107051527_OUT.json | path=C:\\Users\\UMAR\\IdeaProjects\\billing-engine\\data\\success\\output\\ACC-UPSTATE-101_20260107051527_OUT.json | format=JSON","logger_name":"SUCCESS_LOG","thread_name":"http-nio-8080-exec-4","level":"INFO","level_value":20000,"trace_id":"24c28d472f0ef02f1ede04b5b9dc4dd5","event.domain":"billing","trace_flags":"01","span_id":"539bc28241541b45","log.category":"data.output"}
{"@timestamp":"2026-01-07T05:15:27.7577869+05:30","@version":"1","message":"PROCESSING_SUCCESS | account=ACC-UPSTATE-101 | totalDue=65.56","logger_name":"SUCCESS_LOG","thread_name":"http-nio-8080-exec-4","level":"INFO","level_value":20000,"trace_id":"24c28d472f0ef02f1ede04b5b9dc4dd5","event.domain":"billing","trace_flags":"01","span_id":"539bc28241541b45","log.category":"process.success"}
{"@timestamp":"2026-01-07T05:48:20.8808502+05:30","@version":"1","message":"OUTPUT_STORED | file=ACC123_20260107054820_OUT.json | path=C:\\Users\\UMAR\\IdeaProjects\\billing-engine\\data\\success\\output\\ACC123_20260107054820_OUT.json | format=JSON","logger_name":"SUCCESS_LOG","thread_name":"main","level":"INFO","level_value":20000,"event.domain":"billing","log.category":"data.output"}
{"@timestamp":"2026-01-07T05:48:20.8828192+05:30","@version":"1","message":"PROCESSING_SUCCESS | account=ACC123 | totalDue=36.40","logger_name":"SUCCESS_LOG","thread_name":"main","level":"INFO","level_value":20000,"event.domain":"billing","log.category":"process.success"}
{"@timestamp":"2026-01-07T05:52:59.8390124+05:30","@version":"1","message":"OUTPUT_STORED | file=ACC123_20260107055259_OUT.json | path=C:\\Users\\UMAR\\IdeaProjects\\billing-engine\\data\\success\\output\\ACC123_20260107055259_OUT.json | format=JSON","logger_name":"SUCCESS_LOG","thread_name":"main","level":"INFO","level_value":20000,"event.domain":"billing","log.category":"data.output"}
{"@timestamp":"2026-01-07T05:52:59.8400133+05:30","@version":"1","message":"PROCESSING_SUCCESS | account=ACC123 | totalDue=36.40","logger_name":"SUCCESS_LOG","thread_name":"main","level":"INFO","level_value":20000,"event.domain":"billing","log.category":"process.success"}
{"@timestamp":"2026-01-07T05:57:17.1560693+05:30","@version":"1","message":"OUTPUT_STORED | file=ACC123_20260107055717_OUT.json | path=C:\\Users\\UMAR\\IdeaProjects\\billing-engine\\data\\success\\output\\ACC123_20260107055717_OUT.json | format=JSON","logger_name":"SUCCESS_LOG","thread_name":"main","level":"INFO","level_value":20000,"event.domain":"billing","log.category":"data.output"}
{"@timestamp":"2026-01-07T05:57:17.1600704+05:30","@version":"1","message":"PROCESSING_SUCCESS | account=ACC123 | totalDue=36.40","logger_name":"SUCCESS_LOG","thread_name":"main","level":"INFO","level_value":20000,"event.domain":"billing","log.category":"process.success"}
{"@timestamp":"2026-01-07T06:03:33.2774761+05:30","@version":"1","message":"OUTPUT_STORED | file=ACC123_20260107060333_OUT.json | path=C:\\Users\\UMAR\\IdeaProjects\\billing-engine\\data\\success\\output\\ACC123_20260107060333_OUT.json | format=JSON","logger_name":"SUCCESS_LOG","thread_name":"main","level":"INFO","level_value":20000,"event.domain":"billing","log.category":"data.output"}
{"@timestamp":"2026-01-07T06:03:33.2824856+05:30","@version":"1","message":"PROCESSING_SUCCESS | account=ACC123 | totalDue=36.40","logger_name":"SUCCESS_LOG","thread_name":"main","level":"INFO","level_value":20000,"event.domain":"billing","log.category":"process.success"}
{"@timestamp":"2026-01-07T06:10:09.3457509+05:30","@version":"1","message":"OUTPUT_STORED | file=ACC123_20260107061009_OUT.json | path=C:\\Users\\UMAR\\IdeaProjects\\billing-engine\\data\\success\\output\\ACC123_20260107061009_OUT.json | format=JSON","logger_name":"SUCCESS_LOG","thread_name":"main","level":"INFO","level_value":20000,"event.domain":"billing","log.category":"data.output"}
{"@timestamp":"2026-01-07T06:10:09.3467543+05:30","@version":"1","message":"PROCESSING_SUCCESS | account=ACC123 | totalDue=36.40","logger_name":"SUCCESS_LOG","thread_name":"main","level":"INFO","level_value":20000,"event.domain":"billing","log.category":"process.success"}
{"@timestamp":"2026-01-07T06:14:21.7460222+05:30","@version":"1","message":"OUTPUT_STORED | file=ACC123_20260107061421_OUT.json | path=C:\\Users\\UMAR\\IdeaProjects\\billing-engine\\data\\success\\output\\ACC123_20260107061421_OUT.json | format=JSON","logger_name":"SUCCESS_LOG","thread_name":"main","level":"INFO","level_value":20000,"event.domain":"billing","log.category":"data.output"}
{"@timestamp":"2026-01-07T06:14:21.7470237+05:30","@version":"1","message":"PROCESSING_SUCCESS | account=ACC123 | totalDue=36.40","logger_name":"SUCCESS_LOG","thread_name":"main","level":"INFO","level_value":20000,"event.domain":"billing","log.category":"process.success"}
{"@timestamp":"2026-01-07T06:17:51.7977952+05:30","@version":"1","message":"OUTPUT_STORED | file=ACC123_20260107061751_OUT.json | path=C:\\Users\\UMAR\\IdeaProjects\\billing-engine\\data\\success\\output\\ACC123_20260107061751_OUT.json | format=JSON","logger_name":"SUCCESS_LOG","thread_name":"main","level":"INFO","level_value":20000,"event.domain":"billing","log.category":"data.output"}
{"@timestamp":"2026-01-07T06:17:51.8007954+05:30","@version":"1","message":"PROCESSING_SUCCESS | account=ACC123 | totalDue=36.40","logger_name":"SUCCESS_LOG","thread_name":"main","level":"INFO","level_value":20000,"event.domain":"billing","log.category":"process.success"}
{"@timestamp":"2026-01-07T06:25:14.0230903+05:30","@version":"1","message":"OUTPUT_STORED | file=ACC123_20260107062513_OUT.json | path=C:\\Users\\UMAR\\IdeaProjects\\billing-engine\\data\\success\\output\\ACC123_20260107062513_OUT.json | format=JSON","logger_name":"SUCCESS_LOG","thread_name":"main","level":"INFO","level_value":20000,"event.domain":"billing","log.category":"data.output"}
{"@timestamp":"2026-01-07T06:25:14.0280905+05:30","@version":"1","message":"PROCESSING_SUCCESS | account=ACC123 | totalDue=36.40","logger_name":"SUCCESS_LOG","thread_name":"main","level":"INFO","level_value":20000,"event.domain":"billing","log.category":"process.success"}
{"@timestamp":"2026-01-07T06:29:56.8847039+05:30","@version":"1","message":"OUTPUT_STORED | file=ACC123_20260107062956_OUT.json | path=C:\\Users\\UMAR\\IdeaProjects\\billing-engine\\data\\success\\output\\ACC123_20260107062956_OUT.json | format=JSON","logger_name":"SUCCESS_LOG","thread_name":"main","level":"INFO","level_value":20000,"event.domain":"billing","log.category":"data.output"}
{"@timestamp":"2026-01-07T06:29:56.9228461+05:30","@version":"1","message":"PROCESSING_SUCCESS | account=ACC123 | totalDue=36.40","logger_name":"SUCCESS_LOG","thread_name":"main","level":"INFO","level_value":20000,"event.domain":"billing","log.category":"process.success"}
{"@timestamp":"2026-01-07T06:31:00.0044035+05:30","@version":"1","message":"OUTPUT_STORED | file=ACC123_20260107063059_OUT.json | path=C:\\Users\\UMAR\\IdeaProjects\\billing-engine\\data\\success\\output\\ACC123_20260107063059_OUT.json | format=JSON","logger_name":"SUCCESS_LOG","thread_name":"main","level":"INFO","level_value":20000,"event.domain":"billing","log.category":"data.output"}
{"@timestamp":"2026-01-07T06:31:00.0084062+05:30","@version":"1","message":"PROCESSING_SUCCESS | account=ACC123 | totalDue=36.40","logger_name":"SUCCESS_LOG","thread_name":"main","level":"INFO","level_value":20000,"event.domain":"billing","log.category":"process.success"}
{"@timestamp":"2026-01-07T06:33:16.8795233+05:30","@version":"1","message":"OUTPUT_STORED | file=ACC777_20260107063316_OUT.xml | path=C:\\Users\\UMAR\\IdeaProjects\\billing-engine\\data\\success\\output\\ACC777_20260107063316_OUT.xml | format=XML","logger_name":"SUCCESS_LOG","thread_name":"main","level":"INFO","level_value":20000,"event.domain":"billing","log.category":"data.output"}
{"@timestamp":"2026-01-07T06:33:16.8815252+05:30","@version":"1","message":"PROCESSING_SUCCESS | account=ACC777 | totalDue=28.44","logger_name":"SUCCESS_LOG","thread_name":"main","level":"INFO","level_value":20000,"event.domain":"billing","log.category":"process.success"}
{"@timestamp":"2026-01-07T06:33:17.5281846+05:30","@version":"1","message":"OUTPUT_STORED | file=ACC123_OUT.xml | path=C:\\Users\\UMAR\\IdeaProjects\\billing-engine\\data\\success\\output\\ACC123_OUT.xml | format=XML","logger_name":"SUCCESS_LOG","thread_name":"main","level":"INFO","level_value":20000,"event.domain":"billing","log.category":"data.output"}
{"@timestamp":"2026-01-07T06:33:17.529186+05:30","@version":"1","message":"REPLAY_SUCCESS | account=ACC123 | file=ACC123_20260107063100_IN.xml","logger_name":"SUCCESS_LOG","thread_name":"main","level":"INFO","level_value":20000,"event.domain":"billing","log.category":"replay.success"}
{"@timestamp":"2026-01-07T06:33:17.535178+05:30","@version":"1","message":"OUTPUT_STORED | file=ACC999_OUT.xml | path=C:\\Users\\UMAR\\IdeaProjects\\billing-engine\\data\\success\\output\\ACC999_OUT.xml | format=XML","logger_name":"SUCCESS_LOG","thread_name":"main","level":"INFO","level_value":20000,"event.domain":"billing","log.category":"data.output"}
{"@timestamp":"2026-01-07T06:33:17.5361796+05:30","@version":"1","message":"REPLAY_SUCCESS | account=ACC999 | file=ACC999_20260107055259_IN.xml","logger_name":"SUCCESS_LOG","thread_name":"main","level":"INFO","level_value":20000,"event.domain":"billing","log.category":"replay.success"}
{"@timestamp":"2026-01-07T06:33:17.541177+05:30","@version":"1","message":"OUTPUT_STORED | file=ACC999_OUT.xml | path=C:\\Users\\UMAR\\IdeaProjects\\billing-engine\\data\\success\\output\\ACC999_OUT.xml | format=XML","logger_name":"SUCCESS_LOG","thread_name":"main","level":"INFO","level_value":20000,"event.domain":"billing","log.category":"data.output"}
{"@timestamp":"2026-01-07T06:33:17.5421773+05:30","@version":"1","message":"REPLAY_SUCCESS | account=ACC999 | file=ACC999_20260107055716_IN.xml","logger_name":"SUCCESS_LOG","thread_name":"main","level":"INFO","level_value":20000,"event.domain":"billing","log.category":"replay.success"}
{"@timestamp":"2026-01-07T06:33:17.5513577+05:30","@version":"1","message":"OUTPUT_STORED | file=ACC999_OUT.xml | path=C:\\Users\\UMAR\\IdeaProjects\\billing-engine\\data\\success\\output\\ACC999_OUT.xml | format=XML","logger_name":"SUCCESS_LOG","thread_name":"main","level":"INFO","level_value":20000,"event.domain":"billing","log.category":"data.output"}
{"@timestamp":"2026-01-07T06:33:17.5543433+05:30","@version":"1","message":"REPLAY_SUCCESS | account=ACC999 | file=ACC999_20260107060333_IN.xml","logger_name":"SUCCESS_LOG","thread_name":"main","level":"INFO","level_value":20000,"event.domain":"billing","log.category":"replay.success"}
{"@timestamp":"2026-01-07T06:33:17.5623444+05:30","@version":"1","message":"OUTPUT_STORED | file=ACC999_OUT.xml | path=C:\\Users\\UMAR\\IdeaProjects\\billing-engine\\data\\success\\output\\ACC999_OUT.xml | format=XML","logger_name":"SUCCESS_LOG","thread_name":"main","level":"INFO","level_value":20000,"event.domain":"billing","log.category":"data.output"}
{"@timestamp":"2026-01-07T06:33:17.5877708+05:30","@version":"1","message":"REPLAY_SUCCESS | account=ACC999 | file=ACC999_20260107061009_IN.xml","logger_name":"SUCCESS_LOG","thread_name":"main","level":"INFO","level_value":20000,"event.domain":"billing","log.category":"replay.success"}
{"@timestamp":"2026-01-07T06:33:17.5947714+05:30","@version":"1","message":"OUTPUT_STORED | file=ACC999_OUT.xml | path=C:\\Users\\UMAR\\IdeaProjects\\billing-engine\\data\\success\\output\\ACC999_OUT.xml | format=XML","logger_name":"SUCCESS_LOG","thread_name":"main","level":"INFO","level_value":20000,"event.domain":"billing","log.category":"data.output"}
{"@timestamp":"2026-01-07T06:33:17.59577+05:30","@version":"1","message":"REPLAY_SUCCESS | account=ACC999 | file=ACC999_20260107061421_IN.xml","logger_name":"SUCCESS_LOG","thread_name":"main","level":"INFO","level_value":20000,"event.domain":"billing","log.category":"replay.success"}
{"@timestamp":"2026-01-07T06:33:17.6007724+05:30","@version":"1","message":"OUTPUT_STORED | file=ACC999_OUT.xml | path=C:\\Users\\UMAR\\IdeaProjects\\billing-engine\\data\\success\\output\\ACC999_OUT.xml | format=XML","logger_name":"SUCCESS_LOG","thread_name":"main","level":"INFO","level_value":20000,"event.domain":"billing","log.category":"data.output"}
{"@timestamp":"2026-01-07T06:33:17.6027704+05:30","@version":"1","message":"REPLAY_SUCCESS | account=ACC999 | file=ACC999_20260107061751_IN.xml","logger_name":"SUCCESS_LOG","thread_name":"main","level":"INFO","level_value":20000,"event.domain":"billing","log.category":"replay.success"}
{"@timestamp":"2026-01-07T06:33:17.6067721+05:30","@version":"1","message":"OUTPUT_STORED | file=ACC999_OUT.xml | path=C:\\Users\\UMAR\\IdeaProjects\\billing-engine\\data\\success\\output\\ACC999_OUT.xml | format=XML","logger_name":"SUCCESS_LOG","thread_name":"main","level":"INFO","level_value":20000,"event.domain":"billing","log.category":"data.output"}
{"@timestamp":"2026-01-07T06:33:17.6077776+05:30","@version":"1","message":"REPLAY_SUCCESS | account=ACC999 | file=ACC999_20260107062513_IN.xml","logger_name":"SUCCESS_LOG","thread_name":"main","level":"INFO","level_value":20000,"event.domain":"billing","log.category":"replay.success"}
{"@timestamp":"2026-01-07T06:33:17.6121779+05:30","@version":"1","message":"OUTPUT_STORED | file=ACC999_OUT.xml | path=C:\\Users\\UMAR\\IdeaProjects\\billing-engine\\data\\success\\output\\ACC999_OUT.xml | format=XML","logger_name":"SUCCESS_LOG","thread_name":"main","level":"INFO","level_value":20000,"event.domain":"billing","log.category":"data.output"}
{"@timestamp":"2026-01-07T06:33:17.6131746+05:30","@version":"1","message":"REPLAY_SUCCESS | account=ACC999 | file=ACC999_20260107062956_IN.xml","logger_name":"SUCCESS_LOG","thread_name":"main","level":"INFO","level_value":20000,"event.domain":"billing","log.category":"replay.success"}
{"@timestamp":"2026-01-07T06:33:17.6171737+05:30","@version":"1","message":"OUTPUT_STORED | file=ACC999_OUT.xml | path=C:\\Users\\UMAR\\IdeaProjects\\billing-engine\\data\\success\\output\\ACC999_OUT.xml | format=XML","logger_name":"SUCCESS_LOG","thread_name":"main","level":"INFO","level_value":20000,"event.domain":"billing","log.category":"data.output"}
{"@timestamp":"2026-01-07T06:33:17.6182991+05:30","@version":"1","message":"REPLAY_SUCCESS | account=ACC999 | file=ACC999_20260107063059_IN.xml","logger_name":"SUCCESS_LOG","thread_name":"main","level":"INFO","level_value":20000,"event.domain":"billing","log.category":"replay.success"}
{"@timestamp":"2026-01-07T06:33:17.6222943+05:30","@version":"1","message":"OUTPUT_STORED | file=ACC999_OUT.xml | path=C:\\Users\\UMAR\\IdeaProjects\\billing-engine\\data\\success\\output\\ACC999_OUT.xml | format=XML","logger_name":"SUCCESS_LOG","thread_name":"main","level":"INFO","level_value":20000,"event.domain":"billing","log.category":"data.output"}
{"@timestamp":"2026-01-07T06:33:17.6233012+05:30","@version":"1","message":"REPLAY_SUCCESS | account=ACC999 | file=ACC999_20260107063317_IN.xml","logger_name":"SUCCESS_LOG","thread_name":"main","level":"INFO","level_value":20000,"event.domain":"billing","log.category":"replay.success"}
{"@timestamp":"2026-01-07T06:33:17.693186+05:30","@version":"1","message":"OUTPUT_STORED | file=ACC123_20260107063317_OUT.json | path=C:\\Users\\UMAR\\IdeaProjects\\billing-engine\\data\\success\\output\\ACC123_20260107063317_OUT.json | format=JSON","logger_name":"SUCCESS_LOG","thread_name":"main","level":"INFO","level_value":20000,"event.domain":"billing","log.category":"data.output"}
{"@timestamp":"2026-01-07T06:33:17.6981769+05:30","@version":"1","message":"PROCESSING_SUCCESS | account=ACC123 | totalDue=36.40","logger_name":"SUCCESS_LOG","thread_name":"main","level":"INFO","level_value":20000,"event.domain":"billing","log.category":"process.success"}
{"@timestamp":"2026-01-07T06:34:27.1280046+05:30","@version":"1","message":"OUTPUT_STORED | file=ACC777_20260107063427_OUT.xml | path=C:\\Users\\UMAR\\IdeaProjects\\billing-engine\\data\\success\\output\\ACC777_20260107063427_OUT.xml | format=XML","logger_name":"SUCCESS_LOG","thread_name":"main","level":"INFO","level_value":20000,"event.domain":"billing","log.category":"data.output"}
{"@timestamp":"2026-01-07T06:34:27.1310205+05:30","@version":"1","message":"PROCESSING_SUCCESS | account=ACC777 | totalDue=28.44","logger_name":"SUCCESS_LOG","thread_name":"main","level":"INFO","level_value":20000,"event.domain":"billing","log.category":"process.success"}
{"@timestamp":"2026-01-07T06:34:28.0544046+05:30","@version":"1","message":"OUTPUT_STORED | file=ACC123_OUT.xml | path=C:\\Users\\UMAR\\IdeaProjects\\billing-engine\\data\\success\\output\\ACC123_OUT.xml | format=XML","logger_name":"SUCCESS_LOG","thread_name":"main","level":"INFO","level_value":20000,"event.domain":"billing","log.category":"data.output"}
{"@timestamp":"2026-01-07T06:34:28.0604083+05:30","@version":"1","message":"REPLAY_SUCCESS | account=ACC123 | file=ACC123_20260107063317_IN.xml","logger_name":"SUCCESS_LOG","thread_name":"main","level":"INFO","level_value":20000,"event.domain":"billing","log.category":"replay.success"}
{"@timestamp":"2026-01-07T06:34:28.0738865+05:30","@version":"1","message":"OUTPUT_STORED | file=ACC999_OUT.xml | path=C:\\Users\\UMAR\\IdeaProjects\\billing-engine\\data\\success\\output\\ACC999_OUT.xml | format=XML","logger_name":"SUCCESS_LOG","thread_name":"main","level":"INFO","level_value":20000,"event.domain":"billing","log.category":"data.output"}
{"@timestamp":"2026-01-07T06:34:28.0779089+05:30","@version":"1","message":"REPLAY_SUCCESS | account=ACC999 | file=ACC999_20260107063427_IN.xml","logger_name":"SUCCESS_LOG","thread_name":"main","level":"INFO","level_value":20000,"event.domain":"billing","log.category":"replay.success"}
{"@timestamp":"2026-01-07T06:34:28.2075648+05:30","@version":"1","message":"OUTPUT_STORED | file=ACC123_20260107063428_OUT.json | path=C:\\Users\\UMAR\\IdeaProjects\\billing-engine\\data\\success\\output\\ACC123_20260107063428_OUT.json | format=JSON","logger_name":"SUCCESS_LOG","thread_name":"main","level":"INFO","level_value":20000,"event.domain":"billing","log.category":"data.output"}
{"@timestamp":"2026-01-07T06:34:28.2115613+05:30","@version":"1","message":"PROCESSING_SUCCESS | account=ACC123 | totalDue=36.40","logger_name":"SUCCESS_LOG","thread_name":"main","level":"INFO","level_value":20000,"event.domain":"billing","log.category":"process.success"}
{"@timestamp":"2026-01-07T06:35:24.9756594+05:30","@version":"1","message":"OUTPUT_STORED | file=ACC123_OUT.xml | path=C:\\Users\\UMAR\\IdeaProjects\\billing-engine\\data\\success\\output\\ACC123_OUT.xml | format=XML","logger_name":"SUCCESS_LOG","thread_name":"scheduling-1","level":"INFO","level_value":20000,"trace_id":"298635898ad8a82ca81fa5269fb18afd","event.domain":"billing","trace_flags":"01","span_id":"cfa58817e181b057","log.category":"data.output"}
{"@timestamp":"2026-01-07T06:35:24.9776606+05:30","@version":"1","message":"REPLAY_SUCCESS | account=ACC123 | file=ACC123_20260107063428_IN.xml","logger_name":"SUCCESS_LOG","thread_name":"scheduling-1","level":"INFO","level_value":20000,"trace_id":"298635898ad8a82ca81fa5269fb18afd","event.domain":"billing","trace_flags":"01","span_id":"cfa58817e181b057","log.category":"replay.success"}
{"@timestamp":"2026-01-07T06:35:52.8392615+05:30","@version":"1","message":"OUTPUT_STORED | file=ACC-UPSTATE-101_20260107063552_OUT.json | path=C:\\Users\\UMAR\\IdeaProjects\\billing-engine\\data\\success\\output\\ACC-UPSTATE-101_20260107063552_OUT.json | format=JSON","logger_name":"SUCCESS_LOG","thread_name":"http-nio-8080-exec-1","level":"INFO","level_value":20000,"trace_id":"d6d4a2aea6bdc4372b8d279983429a7a","event.domain":"billing","trace_flags":"01","span_id":"1e7c7a4100948a95","log.category":"data.output"}
{"@timestamp":"2026-01-07T06:35:52.8425196+05:30","@version":"1","message":"PROCESSING_SUCCESS | account=ACC-UPSTATE-101 | totalDue=65.56","logger_name":"SUCCESS_LOG","thread_name":"http-nio-8080-exec-1","level":"INFO","level_value":20000,"trace_id":"d6d4a2aea6bdc4372b8d279983429a7a","event.domain":"billing","trace_flags":"01","span_id":"1e7c7a4100948a95","log.category":"process.success"}
{"@timestamp":"2026-01-07T06:35:53.8306463+05:30","@version":"1","message":"OUTPUT_STORED | file=ACC-UPSTATE-101_20260107063553_OUT.json | path=C:\\Users\\UMAR\\IdeaProjects\\billing-engine\\data\\success\\output\\ACC-UPSTATE-101_20260107063553_OUT.json | format=JSON","logger_name":"SUCCESS_LOG","thread_name":"http-nio-8080-exec-3","level":"INFO","level_value":20000,"trace_id":"c2157e0379f581ecc4b9ed5107b2660d","event.domain":"billing","trace_flags":"01","span_id":"69e50b1dbda99ef3","log.category":"data.output"}
{"@timestamp":"2026-01-07T06:35:53.8346472+05:30","@version":"1","message":"PROCESSING_SUCCESS | account=ACC-UPSTATE-101 | totalDue=65.56","logger_name":"SUCCESS_LOG","thread_name":"http-nio-8080-exec-3","level":"INFO","level_value":20000,"trace_id":"c2157e0379f581ecc4b9ed5107b2660d","event.domain":"billing","trace_flags":"01","span_id":"69e50b1dbda99ef3","log.category":"process.success"}
{"@timestamp":"2026-01-07T06:35:55.016386+05:30","@version":"1","message":"OUTPUT_STORED | file=ACC-UPSTATE-101_20260107063554_OUT.json | path=C:\\Users\\UMAR\\IdeaProjects\\billing-engine\\data\\success\\output\\ACC-UPSTATE-101_20260107063554_OUT.json | format=JSON","logger_name":"SUCCESS_LOG","thread_name":"http-nio-8080-exec-4","level":"INFO","level_value":20000,"trace_id":"c0d73ca2d0d546731031013fa4dc62e9","event.domain":"billing","trace_flags":"01","span_id":"47f68ba4009b8b05","log.category":"data.output"}
{"@timestamp":"2026-01-07T06:35:55.0242786+05:30","@version":"1","message":"PROCESSING_SUCCESS | account=ACC-UPSTATE-101 | totalDue=65.56","logger_name":"SUCCESS_LOG","thread_name":"http-nio-8080-exec-4","level":"INFO","level_value":20000,"trace_id":"c0d73ca2d0d546731031013fa4dc62e9","event.domain":"billing","trace_flags":"01","span_id":"47f68ba4009b8b05","log.category":"process.success"}
{"@timestamp":"2026-01-07T06:37:25.031628+05:30","@version":"1","message":"OUTPUT_STORED | file=ACC-UPSTATE-101_OUT.xml | path=C:\\Users\\UMAR\\IdeaProjects\\billing-engine\\data\\success\\output\\ACC-UPSTATE-101_OUT.xml | format=XML","logger_name":"SUCCESS_LOG","thread_name":"scheduling-1","level":"INFO","level_value":20000,"trace_id":"34885d169193804a018c0a6d6febcbf5","event.domain":"billing","trace_flags":"01","span_id":"13ae6bd943b861a5","log.category":"data.output"}
{"@timestamp":"2026-01-07T06:37:25.031628+05:30","@version":"1","message":"REPLAY_SUCCESS | account=ACC-UPSTATE-101 | file=ACC-UPSTATE-101_20260107063614_IN.xml","logger_name":"SUCCESS_LOG","thread_name":"scheduling-1","level":"INFO","level_value":20000,"trace_id":"34885d169193804a018c0a6d6febcbf5","event.domain":"billing","trace_flags":"01","span_id":"13ae6bd943b861a5","log.category":"replay.success"}
{"@timestamp":"2026-01-07T06:37:25.0476812+05:30","@version":"1","message":"OUTPUT_STORED | file=ACC-UPSTATE-101_OUT.xml | path=C:\\Users\\UMAR\\IdeaProjects\\billing-engine\\data\\success\\output\\ACC-UPSTATE-101_OUT.xml | format=XML","logger_name":"SUCCESS_LOG","thread_name":"scheduling-1","level":"INFO","level_value":20000,"trace_id":"34885d169193804a018c0a6d6febcbf5","event.domain":"billing","trace_flags":"01","span_id":"13ae6bd943b861a5","log.category":"data.output"}
{"@timestamp":"2026-01-07T06:37:25.063728+05:30","@version":"1","message":"REPLAY_SUCCESS | account=ACC-UPSTATE-101 | file=ACC-UPSTATE-101_20260107063615_IN.xml","logger_name":"SUCCESS_LOG","thread_name":"scheduling-1","level":"INFO","level_value":20000,"trace_id":"34885d169193804a018c0a6d6febcbf5","event.domain":"billing","trace_flags":"01","span_id":"13ae6bd943b861a5","log.category":"replay.success"}
{"@timestamp":"2026-01-07T06:37:25.072251+05:30","@version":"1","message":"OUTPUT_STORED | file=ACC-UPSTATE-101_OUT.xml | path=C:\\Users\\UMAR\\IdeaProjects\\billing-engine\\data\\success\\output\\ACC-UPSTATE-101_OUT.xml | format=XML","logger_name":"SUCCESS_LOG","thread_name":"scheduling-1","level":"INFO","level_value":20000,"trace_id":"34885d169193804a018c0a6d6febcbf5","event.domain":"billing","trace_flags":"01","span_id":"13ae6bd943b861a5","log.category":"data.output"}
{"@timestamp":"2026-01-07T06:37:25.0873488+05:30","@version":"1","message":"REPLAY_SUCCESS | account=ACC-UPSTATE-101 | file=ACC-UPSTATE-101_20260107063616_IN.xml","logger_name":"SUCCESS_LOG","thread_name":"scheduling-1","level":"INFO","level_value":20000,"trace_id":"34885d169193804a018c0a6d6febcbf5","event.domain":"billing","trace_flags":"01","span_id":"13ae6bd943b861a5","log.category":"replay.success"}
{"@timestamp":"2026-01-07T06:49:14.3266043+05:30","@version":"1","message":"OUTPUT_STORED | file=ACC-UPSTATE-101_20260107064914_OUT.json | path=C:\\Users\\UMAR\\IdeaProjects\\billing-engine\\data\\success\\output\\ACC-UPSTATE-101_20260107064914_OUT.json | format=JSON","logger_name":"SUCCESS_LOG","thread_name":"http-nio-8080-exec-2","level":"INFO","level_value":20000,"trace_id":"5c4028d717ccf9a3b7b5a6740eb6d5ec","event.domain":"billing","trace_flags":"01","span_id":"a163ca0f49c497eb","log.category":"data.output"}
{"@timestamp":"2026-01-07T06:49:14.3403262+05:30","@version":"1","message":"PROCESSING_SUCCESS | account=ACC-UPSTATE-101 | totalDue=65.56","logger_name":"SUCCESS_LOG","thread_name":"http-nio-8080-exec-2","level":"INFO","level_value":20000,"trace_id":"5c4028d717ccf9a3b7b5a6740eb6d5ec","event.domain":"billing","trace_flags":"01","span_id":"a163ca0f49c497eb","log.category":"process.success"}
{"@timestamp":"2026-01-07T06:49:16.0810023+05:30","@version":"1","message":"OUTPUT_STORED | file=ACC-UPSTATE-101_20260107064916_OUT.json | path=C:\\Users\\UMAR\\IdeaProjects\\billing-engine\\data\\success\\output\\ACC-UPSTATE-101_20260107064916_OUT.json | format=JSON","logger_name":"SUCCESS_LOG","thread_name":"http-nio-8080-exec-3","level":"INFO","level_value":20000,"trace_id":"9d285eb27c5b8e14ba9a2b5ebba7a647","event.domain":"billing","trace_flags":"01","span_id":"e000d688d55f0b18","log.category":"data.output"}
{"@timestamp":"2026-01-07T06:49:16.0850611+05:30","@version":"1","message":"PROCESSING_SUCCESS | account=ACC-UPSTATE-101 | totalDue=65.56","logger_name":"SUCCESS_LOG","thread_name":"http-nio-8080-exec-3","level":"INFO","level_value":20000,"trace_id":"9d285eb27c5b8e14ba9a2b5ebba7a647","event.domain":"billing","trace_flags":"01","span_id":"e000d688d55f0b18","log.category":"process.success"}
{"@timestamp":"2026-01-07T06:49:17.3084923+05:30","@version":"1","message":"OUTPUT_STORED | file=ACC-UPSTATE-101_20260107064917_OUT.json | path=C:\\Users\\UMAR\\IdeaProjects\\billing-engine\\data\\success\\output\\ACC-UPSTATE-101_20260107064917_OUT.json | format=JSON","logger_name":"SUCCESS_LOG","thread_name":"http-nio-8080-exec-4","level":"INFO","level_value":20000,"trace_id":"cc9c680201a92cecfb17109aeac210b0","event.domain":"billing","trace_flags":"01","span_id":"28daeeeaf5a51535","log.category":"data.output"}
{"@timestamp":"2026-01-07T06:49:17.3165155+05:30","@version":"1","message":"PROCESSING_SUCCESS | account=ACC-UPSTATE-101 | totalDue=65.56","logger_name":"SUCCESS_LOG","thread_name":"http-nio-8080-exec-4","level":"INFO","level_value":20000,"trace_id":"cc9c680201a92cecfb17109aeac210b0","event.domain":"billing","trace_flags":"01","span_id":"28daeeeaf5a51535","log.category":"process.success"}
{"@timestamp":"2026-01-07T06:50:51.6836168+05:30","@version":"1","message":"OUTPUT_STORED | file=ACC-UPSTATE-101_OUT.xml | path=C:\\Users\\UMAR\\IdeaProjects\\billing-engine\\data\\success\\output\\ACC-UPSTATE-101_OUT.xml | format=XML","logger_name":"SUCCESS_LOG","thread_name":"scheduling-1","level":"INFO","level_value":20000,"trace_id":"8733d40e6e347b9c12e3b418125bccac","event.domain":"billing","trace_flags":"01","span_id":"f4f2aa9d5fcb6630","log.category":"data.output"}
{"@timestamp":"2026-01-07T06:50:51.6993662+05:30","@version":"1","message":"REPLAY_SUCCESS | account=ACC-UPSTATE-101 | file=ACC-UPSTATE-101_20260107064945_IN.xml","logger_name":"SUCCESS_LOG","thread_name":"scheduling-1","level":"INFO","level_value":20000,"trace_id":"8733d40e6e347b9c12e3b418125bccac","event.domain":"billing","trace_flags":"01","span_id":"f4f2aa9d5fcb6630","log.category":"replay.success"}
{"@timestamp":"2026-01-07T06:50:51.7151364+05:30","@version":"1","message":"OUTPUT_STORED | file=ACC-UPSTATE-101_OUT.xml | path=C:\\Users\\UMAR\\IdeaProjects\\billing-engine\\data\\success\\output\\ACC-UPSTATE-101_OUT.xml | format=XML","logger_name":"SUCCESS_LOG","thread_name":"scheduling-1","level":"INFO","level_value":20000,"trace_id":"8733d40e6e347b9c12e3b418125bccac","event.domain":"billing","trace_flags":"01","span_id":"f4f2aa9d5fcb6630","log.category":"data.output"}
{"@timestamp":"2026-01-07T06:50:51.7151364+05:30","@version":"1","message":"REPLAY_SUCCESS | account=ACC-UPSTATE-101 | file=ACC-UPSTATE-101_20260107064946_IN.xml","logger_name":"SUCCESS_LOG","thread_name":"scheduling-1","level":"INFO","level_value":20000,"trace_id":"8733d40e6e347b9c12e3b418125bccac","event.domain":"billing","trace_flags":"01","span_id":"f4f2aa9d5fcb6630","log.category":"replay.success"}
{"@timestamp":"2026-01-07T06:50:51.7308367+05:30","@version":"1","message":"OUTPUT_STORED | file=ACC-UPSTATE-101_OUT.xml | path=C:\\Users\\UMAR\\IdeaProjects\\billing-engine\\data\\success\\output\\ACC-UPSTATE-101_OUT.xml | format=XML","logger_name":"SUCCESS_LOG","thread_name":"scheduling-1","level":"INFO","level_value":20000,"trace_id":"8733d40e6e347b9c12e3b418125bccac","event.domain":"billing","trace_flags":"01","span_id":"f4f2aa9d5fcb6630","log.category":"data.output"}
{"@timestamp":"2026-01-07T06:50:51.7469164+05:30","@version":"1","message":"REPLAY_SUCCESS | account=ACC-UPSTATE-101 | file=ACC-UPSTATE-101_20260107064948_IN.xml","logger_name":"SUCCESS_LOG","thread_name":"scheduling-1","level":"INFO","level_value":20000,"trace_id":"8733d40e6e347b9c12e3b418125bccac","event.domain":"billing","trace_flags":"01","span_id":"f4f2aa9d5fcb6630","log.category":"replay.success"}
{"@timestamp":"2026-01-07T06:58:19.9205653+05:30","@version":"1","message":"OUTPUT_STORED | file=ACC-UPSTATE-101_20260107065819_OUT.json | path=C:\\Users\\UMAR\\IdeaProjects\\billing-engine\\data\\success\\output\\ACC-UPSTATE-101_20260107065819_OUT.json | format=JSON","logger_name":"SUCCESS_LOG","thread_name":"http-nio-8080-exec-1","level":"INFO","level_value":20000,"trace_id":"9bb3cc59f3665e9d8aaf8e1feec0dadc","event.domain":"billing","trace_flags":"01","span_id":"7a7b16c9e6eebfc0","log.category":"data.output"}
{"@timestamp":"2026-01-07T06:58:19.9371808+05:30","@version":"1","message":"PROCESSING_SUCCESS | account=ACC-UPSTATE-101 | totalDue=65.56","logger_name":"SUCCESS_LOG","thread_name":"http-nio-8080-exec-1","level":"INFO","level_value":20000,"trace_id":"9bb3cc59f3665e9d8aaf8e1feec0dadc","event.domain":"billing","trace_flags":"01","span_id":"7a7b16c9e6eebfc0","log.category":"process.success"}
{"@timestamp":"2026-01-07T06:58:21.4914183+05:30","@version":"1","message":"OUTPUT_STORED | file=ACC-UPSTATE-101_20260107065821_OUT.json | path=C:\\Users\\UMAR\\IdeaProjects\\billing-engine\\data\\success\\output\\ACC-UPSTATE-101_20260107065821_OUT.json | format=JSON","logger_name":"SUCCESS_LOG","thread_name":"http-nio-8080-exec-3","level":"INFO","level_value":20000,"trace_id":"478ba928b594a90ab853696cc6b4ab2d","event.domain":"billing","trace_flags":"01","span_id":"a7859902b40cb4ad","log.category":"data.output"}
{"@timestamp":"2026-01-07T06:58:21.4990348+05:30","@version":"1","message":"PROCESSING_SUCCESS | account=ACC-UPSTATE-101 | totalDue=65.56","logger_name":"SUCCESS_LOG","thread_name":"http-nio-8080-exec-3","level":"INFO","level_value":20000,"trace_id":"478ba928b594a90ab853696cc6b4ab2d","event.domain":"billing","trace_flags":"01","span_id":"a7859902b40cb4ad","log.category":"process.success"}
{"@timestamp":"2026-01-07T06:58:29.7020428+05:30","@version":"1","message":"OUTPUT_STORED | file=ACC-UPSTATE-101_20260107065829_OUT.json | path=C:\\Users\\UMAR\\IdeaProjects\\billing-engine\\data\\success\\output\\ACC-UPSTATE-101_20260107065829_OUT.json | format=JSON","logger_name":"SUCCESS_LOG","thread_name":"http-nio-8080-exec-4","level":"INFO","level_value":20000,"trace_id":"e0810098b28753f376d90e1bb238142a","event.domain":"billing","trace_flags":"01","span_id":"e2c341adf26f039f","log.category":"data.output"}
{"@timestamp":"2026-01-07T06:58:29.7114055+05:30","@version":"1","message":"PROCESSING_SUCCESS | account=ACC-UPSTATE-101 | totalDue=65.56","logger_name":"SUCCESS_LOG","thread_name":"http-nio-8080-exec-4","level":"INFO","level_value":20000,"trace_id":"e0810098b28753f376d90e1bb238142a","event.domain":"billing","trace_flags":"01","span_id":"e2c341adf26f039f","log.category":"process.success"}
{"@timestamp":"2026-01-07T06:58:56.6370071+05:30","@version":"1","message":"OUTPUT_STORED | file=ACC-UPSTATE-101_20260107065856_OUT.json | path=C:\\Users\\UMAR\\IdeaProjects\\billing-engine\\data\\success\\output\\ACC-UPSTATE-101_20260107065856_OUT.json | format=JSON","logger_name":"SUCCESS_LOG","thread_name":"http-nio-8080-exec-9","level":"INFO","level_value":20000,"trace_id":"625f997934de26f8aae022adccd7208e","event.domain":"billing","trace_flags":"01","span_id":"a5922a16191e86ee","log.category":"data.output"}
{"@timestamp":"2026-01-07T06:58:56.6452008+05:30","@version":"1","message":"PROCESSING_SUCCESS | account=ACC-UPSTATE-101 | totalDue=65.56","logger_name":"SUCCESS_LOG","thread_name":"http-nio-8080-exec-9","level":"INFO","level_value":20000,"trace_id":"625f997934de26f8aae022adccd7208e","event.domain":"billing","trace_flags":"01","span_id":"a5922a16191e86ee","log.category":"process.success"}
{"@timestamp":"2026-01-07T06:58:57.5884951+05:30","@version":"1","message":"OUTPUT_STORED | file=ACC-UPSTATE-101_20260107065857_OUT.json | path=C:\\Users\\UMAR\\IdeaProjects\\billing-engine\\data\\success\\output\\ACC-UPSTATE-101_20260107065857_OUT.json | format=JSON","logger_name":"SUCCESS_LOG","thread_name":"http-nio-8080-exec-10","level":"INFO","level_value":20000,"trace_id":"fbd8ceeb967e530a7d6f0e85169a0367","event.domain":"billing","trace_flags":"01","span_id":"739fb9b0f23888a4","log.category":"data.output"}
{"@timestamp":"2026-01-07T06:58:57.5966152+05:30","@version":"1","message":"PROCESSING_SUCCESS | account=ACC-UPSTATE-101 | totalDue=65.56","logger_name":"SUCCESS_LOG","thread_name":"http-nio-8080-exec-10","level":"INFO","level_value":20000,"trace_id":"fbd8ceeb967e530a7d6f0e85169a0367","event.domain":"billing","trace_flags":"01","span_id":"739fb9b0f23888a4","log.category":"process.success"}
{"@timestamp":"2026-01-07T06:58:58.5184998+05:30","@version":"1","message":"OUTPUT_STORED | file=ACC-UPSTATE-101_20260107065858_OUT.json | path=C:\\Users\\UMAR\\IdeaProjects\\billing-engine\\data\\success\\output\\ACC-UPSTATE-101_20260107065858_OUT.json | format=JSON","logger_name":"SUCCESS_LOG","thread_name":"http-nio-8080-exec-2","level":"INFO","level_value":20000,"trace_id":"7d18d9680e1dd4e49882901661c1c33c","event.domain":"billing","trace_flags":"01","span_id":"a33153183fd84bb6","log.category":"data.output"}
{"@timestamp":"2026-01-07T06:58:58.5184998+05:30","@version":"1","message":"PROCESSING_SUCCESS | account=ACC-UPSTATE-101 | totalDue=65.56","logger_name":"SUCCESS_LOG","thread_name":"http-nio-8080-exec-2","level":"INFO","level_value":20000,"trace_id":"7d18d9680e1dd4e49882901661c1c33c","event.domain":"billing","trace_flags":"01","span_id":"a33153183fd84bb6","log.category":"process.success"}
{"@timestamp":"2026-01-07T07:09:09.4320275+05:30","@version":"1","message":"OUTPUT_STORED | file=ACC-UPSTATE-101_20260107070909_OUT.json | path=C:\\Users\\UMAR\\IdeaProjects\\billing-engine\\data\\success\\output\\ACC-UPSTATE-101_20260107070909_OUT.json | format=JSON","logger_name":"SUCCESS_LOG","thread_name":"http-nio-8080-exec-2","level":"INFO","level_value":20000,"trace_id":"9117319041a901c2ba3ba3154b34a1cb","event.domain":"billing","trace_flags":"01","span_id":"6d0a75eec9026e53","log.category":"data.output"}
{"@timestamp":"2026-01-07T07:09:09.4393135+05:30","@version":"1","message":"PROCESSING_SUCCESS | account=ACC-UPSTATE-101 | totalDue=65.56","logger_name":"SUCCESS_LOG","thread_name":"http-nio-8080-exec-2","level":"INFO","level_value":20000,"trace_id":"9117319041a901c2ba3ba3154b34a1cb","event.domain":"billing","trace_flags":"01","span_id":"6d0a75eec9026e53","log.category":"process.success"}
{"@timestamp":"2026-01-07T07:09:10.3960905+05:30","@version":"1","message":"OUTPUT_STORED | file=ACC-UPSTATE-101_20260107070910_OUT.json | path=C:\\Users\\UMAR\\IdeaProjects\\billing-engine\\data\\success\\output\\ACC-UPSTATE-101_20260107070910_OUT.json | format=JSON","logger_name":"SUCCESS_LOG","thread_name":"http-nio-8080-exec-3","level":"INFO","level_value":20000,"trace_id":"7a534d3acb73a812612784ca4b22aaaa","event.domain":"billing","trace_flags":"01","span_id":"c257d39c04ec8a0d","log.category":"data.output"}
{"@timestamp":"2026-01-07T07:09:10.3991179+05:30","@version":"1","message":"PROCESSING_SUCCESS | account=ACC-UPSTATE-101 | totalDue=65.56","logger_name":"SUCCESS_LOG","thread_name":"http-nio-8080-exec-3","level":"INFO","level_value":20000,"trace_id":"7a534d3acb73a812612784ca4b22aaaa","event.domain":"billing","trace_flags":"01","span_id":"c257d39c04ec8a0d","log.category":"process.success"}
{"@timestamp":"2026-01-07T07:09:12.3513894+05:30","@version":"1","message":"OUTPUT_STORED | file=ACC-UPSTATE-101_20260107070912_OUT.json | path=C:\\Users\\UMAR\\IdeaProjects\\billing-engine\\data\\success\\output\\ACC-UPSTATE-101_20260107070912_OUT.json | format=JSON","logger_name":"SUCCESS_LOG","thread_name":"http-nio-8080-exec-4","level":"INFO","level_value":20000,"trace_id":"589a550c1df9f1ae1a7a5287538d4e18","event.domain":"billing","trace_flags":"01","span_id":"c5e421182cf2b5a9","log.category":"data.output"}
{"@timestamp":"2026-01-07T07:09:12.3555982+05:30","@version":"1","message":"PROCESSING_SUCCESS | account=ACC-UPSTATE-101 | totalDue=65.56","logger_name":"SUCCESS_LOG","thread_name":"http-nio-8080-exec-4","level":"INFO","level_value":20000,"trace_id":"589a550c1df9f1ae1a7a5287538d4e18","event.domain":"billing","trace_flags":"01","span_id":"c5e421182cf2b5a9","log.category":"process.success"}
{"@timestamp":"2026-01-07T07:09:38.4107353+05:30","@version":"1","message":"OUTPUT_STORED | file=ACC-UPSTATE-101_20260107070938_OUT.json | path=C:\\Users\\UMAR\\IdeaProjects\\billing-engine\\data\\success\\output\\ACC-UPSTATE-101_20260107070938_OUT.json | format=JSON","logger_name":"SUCCESS_LOG","thread_name":"http-nio-8080-exec-9","level":"INFO","level_value":20000,"trace_id":"47194a23c6b195b07241accb36d23b3c","event.domain":"billing","trace_flags":"01","span_id":"b979eae876ed3524","log.category":"data.output"}
{"@timestamp":"2026-01-07T07:09:38.4231073+05:30","@version":"1","message":"PROCESSING_SUCCESS | account=ACC-UPSTATE-101 | totalDue=65.56","logger_name":"SUCCESS_LOG","thread_name":"http-nio-8080-exec-9","level":"INFO","level_value":20000,"trace_id":"47194a23c6b195b07241accb36d23b3c","event.domain":"billing","trace_flags":"01","span_id":"b979eae876ed3524","log.category":"process.success"}
{"@timestamp":"2026-01-07T07:09:39.5523744+05:30","@version":"1","message":"OUTPUT_STORED | file=ACC-UPSTATE-101_20260107070939_OUT.json | path=C:\\Users\\UMAR\\IdeaProjects\\billing-engine\\data\\success\\output\\ACC-UPSTATE-101_20260107070939_OUT.json | format=JSON","logger_name":"SUCCESS_LOG","thread_name":"http-nio-8080-exec-10","level":"INFO","level_value":20000,"trace_id":"882023b6010759e78a88d7a4e74282f4","event.domain":"billing","trace_flags":"01","span_id":"d7892efa9843d061","log.category":"data.output"}
{"@timestamp":"2026-01-07T07:09:39.5605107+05:30","@version":"1","message":"PROCESSING_SUCCESS | account=ACC-UPSTATE-101 | totalDue=65.56","logger_name":"SUCCESS_LOG","thread_name":"http-nio-8080-exec-10","level":"INFO","level_value":20000,"trace_id":"882023b6010759e78a88d7a4e74282f4","event.domain":"billing","trace_flags":"01","span_id":"d7892efa9843d061","log.category":"process.success"}
{"@timestamp":"2026-01-07T07:09:40.5493101+05:30","@version":"1","message":"OUTPUT_STORED | file=ACC-UPSTATE-101_20260107070940_OUT.json | path=C:\\Users\\UMAR\\IdeaProjects\\billing-engine\\data\\success\\output\\ACC-UPSTATE-101_20260107070940_OUT.json | format=JSON","logger_name":"SUCCESS_LOG","thread_name":"http-nio-8080-exec-1","level":"INFO","level_value":20000,"trace_id":"a807c348983fa7c196801752cd0818f9","event.domain":"billing","trace_flags":"01","span_id":"4fcdf6baa4bc264b","log.category":"data.output"}
{"@timestamp":"2026-01-07T07:09:40.5578051+05:30","@version":"1","message":"PROCESSING_SUCCESS | account=ACC-UPSTATE-101 | totalDue=65.56","logger_name":"SUCCESS_LOG","thread_name":"http-nio-8080-exec-1","level":"INFO","level_value":20000,"trace_id":"a807c348983fa7c196801752cd0818f9","event.domain":"billing","trace_flags":"01","span_id":"4fcdf6baa4bc264b","log.category":"process.success"}
{"@timestamp":"2026-01-07T07:16:57.957141+05:30","@version":"1","message":"OUTPUT_STORED | file=ACC-UPSTATE-101_20260107071657_OUT.json | path=C:\\Users\\UMAR\\IdeaProjects\\billing-engine\\data\\success\\output\\ACC-UPSTATE-101_20260107071657_OUT.json | format=JSON","logger_name":"SUCCESS_LOG","thread_name":"http-nio-8080-exec-5","level":"INFO","level_value":20000,"trace_id":"5a6092062ecef0d9b675ff274bbdab1b","event.domain":"billing","trace_flags":"01","span_id":"bae2cb2ad4839f70","log.category":"data.output"}
{"@timestamp":"2026-01-07T07:16:57.9631375+05:30","@version":"1","message":"PROCESSING_SUCCESS | account=ACC-UPSTATE-101 | totalDue=65.56","logger_name":"SUCCESS_LOG","thread_name":"http-nio-8080-exec-5","level":"INFO","level_value":20000,"trace_id":"5a6092062ecef0d9b675ff274bbdab1b","event.domain":"billing","trace_flags":"01","span_id":"bae2cb2ad4839f70","log.category":"process.success"}
{"@timestamp":"2026-01-07T07:16:58.7262647+05:30","@version":"1","message":"OUTPUT_STORED | file=ACC-UPSTATE-101_20260107071658_OUT.json | path=C:\\Users\\UMAR\\IdeaProjects\\billing-engine\\data\\success\\output\\ACC-UPSTATE-101_20260107071658_OUT.json | format=JSON","logger_name":"SUCCESS_LOG","thread_name":"http-nio-8080-exec-8","level":"INFO","level_value":20000,"trace_id":"4abc3e07865858997703039dadead645","event.domain":"billing","trace_flags":"01","span_id":"7e987ec0e1c24516","log.category":"data.output"}
{"@timestamp":"2026-01-07T07:16:58.7322229+05:30","@version":"1","message":"PROCESSING_SUCCESS | account=ACC-UPSTATE-101 | totalDue=65.56","logger_name":"SUCCESS_LOG","thread_name":"http-nio-8080-exec-8","level":"INFO","level_value":20000,"trace_id":"4abc3e07865858997703039dadead645","event.domain":"billing","trace_flags":"01","span_id":"7e987ec0e1c24516","log.category":"process.success"}
{"@timestamp":"2026-01-07T07:16:59.3759017+05:30","@version":"1","message":"OUTPUT_STORED | file=ACC-UPSTATE-101_20260107071659_OUT.json | path=C:\\Users\\UMAR\\IdeaProjects\\billing-engine\\data\\success\\output\\ACC-UPSTATE-101_20260107071659_OUT.json | format=JSON","logger_name":"SUCCESS_LOG","thread_name":"http-nio-8080-exec-7","level":"INFO","level_value":20000,"trace_id":"1dfb2e13ce56296a21ad5c9a0652c8f7","event.domain":"billing","trace_flags":"01","span_id":"0cd18a4466883f04","log.category":"data.output"}
{"@timestamp":"2026-01-07T07:16:59.3800271+05:30","@version":"1","message":"PROCESSING_SUCCESS | account=ACC-UPSTATE-101 | totalDue=65.56","logger_name":"SUCCESS_LOG","thread_name":"http-nio-8080-exec-7","level":"INFO","level_value":20000,"trace_id":"1dfb2e13ce56296a21ad5c9a0652c8f7","event.domain":"billing","trace_flags":"01","span_id":"0cd18a4466883f04","log.category":"process.success"}
{"@timestamp":"2026-01-07T07:17:00.062679+05:30","@version":"1","message":"OUTPUT_STORED | file=ACC-UPSTATE-101_20260107071700_OUT.json | path=C:\\Users\\UMAR\\IdeaProjects\\billing-engine\\data\\success\\output\\ACC-UPSTATE-101_20260107071700_OUT.json | format=JSON","logger_name":"SUCCESS_LOG","thread_name":"http-nio-8080-exec-6","level":"INFO","level_value":20000,"trace_id":"559c46b84b6716133fff42aa99cf1cea","event.domain":"billing","trace_flags":"01","span_id":"bb5b347ae0bb6b88","log.category":"data.output"}
{"@timestamp":"2026-01-07T07:17:00.0668087+05:30","@version":"1","message":"PROCESSING_SUCCESS | account=ACC-UPSTATE-101 | totalDue=65.56","logger_name":"SUCCESS_LOG","thread_name":"http-nio-8080-exec-6","level":"INFO","level_value":20000,"trace_id":"559c46b84b6716133fff42aa99cf1cea","event.domain":"billing","trace_flags":"01","span_id":"bb5b347ae0bb6b88","log.category":"process.success"}
{"@timestamp":"2026-01-07T07:17:00.7791825+05:30","@version":"1","message":"OUTPUT_STORED | file=ACC-UPSTATE-101_20260107071700_OUT.json | path=C:\\Users\\UMAR\\IdeaProjects\\billing-engine\\data\\success\\output\\ACC-UPSTATE-101_20260107071700_OUT.json | format=JSON","logger_name":"SUCCESS_LOG","thread_name":"http-nio-8080-exec-9","level":"INFO","level_value":20000,"trace_id":"9a3324773bf0133bb4a4fe66b989e9ff","event.domain":"billing","trace_flags":"01","span_id":"7065281042315441","log.category":"data.output"}
{"@timestamp":"2026-01-07T07:17:00.7837733+05:30","@version":"1","message":"PROCESSING_SUCCESS | account=ACC-UPSTATE-101 | totalDue=65.56","logger_name":"SUCCESS_LOG","thread_name":"http-nio-8080-exec-9","level":"INFO","level_value":20000,"trace_id":"9a3324773bf0133bb4a4fe66b989e9ff","event.domain":"billing","trace_flags":"01","span_id":"7065281042315441","log.category":"process.success"}
{"@timestamp":"2026-01-07T07:17:01.4277496+05:30","@version":"1","message":"OUTPUT_STORED | file=ACC-UPSTATE-101_20260107071701_OUT.json | path=C:\\Users\\UMAR\\IdeaProjects\\billing-engine\\data\\success\\output\\ACC-UPSTATE-101_20260107071701_OUT.json | format=JSON","logger_name":"SUCCESS_LOG","thread_name":"http-nio-8080-exec-10","level":"INFO","level_value":20000,"trace_id":"0469d5082950ac7eefb07fc5c4a98bfd","event.domain":"billing","trace_flags":"01","span_id":"9eaef577625a77fe","log.category":"data.output"}
{"@timestamp":"2026-01-07T07:17:01.4307397+05:30","@version":"1","message":"PROCESSING_SUCCESS | account=ACC-UPSTATE-101 | totalDue=65.56","logger_name":"SUCCESS_LOG","thread_name":"http-nio-8080-exec-10","level":"INFO","level_value":20000,"trace_id":"0469d5082950ac7eefb07fc5c4a98bfd","event.domain":"billing","trace_flags":"01","span_id":"9eaef577625a77fe","log.category":"process.success"}
{"@timestamp":"2026-01-07T07:17:02.2923979+05:30","@version":"1","message":"OUTPUT_STORED | file=ACC-UPSTATE-101_20260107071702_OUT.json | path=C:\\Users\\UMAR\\IdeaProjects\\billing-engine\\data\\success\\output\\ACC-UPSTATE-101_20260107071702_OUT.json | format=JSON","logger_name":"SUCCESS_LOG","thread_name":"http-nio-8080-exec-1","level":"INFO","level_value":20000,"trace_id":"b8134f528bb46e4f489cd1123c7a5863","event.domain":"billing","trace_flags":"01","span_id":"dd27ac8a6fb213e0","log.category":"data.output"}
{"@timestamp":"2026-01-07T07:17:02.3130772+05:30","@version":"1","message":"PROCESSING_SUCCESS | account=ACC-UPSTATE-101 | totalDue=65.56","logger_name":"SUCCESS_LOG","thread_name":"http-nio-8080-exec-1","level":"INFO","level_value":20000,"trace_id":"b8134f528bb46e4f489cd1123c7a5863","event.domain":"billing","trace_flags":"01","span_id":"dd27ac8a6fb213e0","log.category":"process.success"}
{"@timestamp":"2026-01-07T09:21:17.8454633+05:30","@version":"1","message":"OUTPUT_STORED | file=ACC777_20260107092117_OUT.xml | path=C:\\Users\\UMAR\\IdeaProjects\\billing-engine\\data\\success\\output\\ACC777_20260107092117_OUT.xml | format=XML","logger_name":"SUCCESS_LOG","thread_name":"main","level":"INFO","level_value":20000,"event.domain":"billing","log.category":"data.output"}
{"@timestamp":"2026-01-07T09:21:17.8464614+05:30","@version":"1","message":"PROCESSING_SUCCESS | account=ACC777 | totalDue=28.44","logger_name":"SUCCESS_LOG","thread_name":"main","level":"INFO","level_value":20000,"event.domain":"billing","log.category":"process.success"}
{"@timestamp":"2026-01-07T09:21:18.5778351+05:30","@version":"1","message":"OUTPUT_STORED | file=ACC999_OUT.xml | path=C:\\Users\\UMAR\\IdeaProjects\\billing-engine\\data\\success\\output\\ACC999_OUT.xml | format=XML","logger_name":"SUCCESS_LOG","thread_name":"main","level":"INFO","level_value":20000,"event.domain":"billing","log.category":"data.output"}
{"@timestamp":"2026-01-07T09:21:18.5798375+05:30","@version":"1","message":"REPLAY_SUCCESS | account=ACC999 | file=ACC999_20260107092118_IN.xml","logger_name":"SUCCESS_LOG","thread_name":"main","level":"INFO","level_value":20000,"event.domain":"billing","log.category":"replay.success"}
{"@timestamp":"2026-01-07T09:21:18.6725262+05:30","@version":"1","message":"OUTPUT_STORED | file=ACC123_20260107092118_OUT.json | path=C:\\Users\\UMAR\\IdeaProjects\\billing-engine\\data\\success\\output\\ACC123_20260107092118_OUT.json | format=JSON","logger_name":"SUCCESS_LOG","thread_name":"main","level":"INFO","level_value":20000,"event.domain":"billing","log.category":"data.output"}
{"@timestamp":"2026-01-07T09:21:18.6755258+05:30","@version":"1","message":"PROCESSING_SUCCESS | account=ACC123 | totalDue=36.40","logger_name":"SUCCESS_LOG","thread_name":"main","level":"INFO","level_value":20000,"event.domain":"billing","log.category":"process.success"}
{"@timestamp":"2026-01-07T09:24:59.150504+05:30","@version":"1","message":"OUTPUT_STORED | file=ACC123_OUT.xml | path=C:\\Users\\UMAR\\IdeaProjects\\billing-engine\\data\\success\\output\\ACC123_OUT.xml | format=XML","logger_name":"SUCCESS_LOG","thread_name":"scheduling-1","level":"INFO","level_value":20000,"trace_id":"1e38162b265be8c100ab58b1bf1c76bf","event.domain":"billing","trace_flags":"01","span_id":"bc70ff86eaa41fe3","log.category":"data.output"}
{"@timestamp":"2026-01-07T09:24:59.1524539+05:30","@version":"1","message":"REPLAY_SUCCESS | account=ACC123 | file=ACC123_20260107092118_IN.xml","logger_name":"SUCCESS_LOG","thread_name":"scheduling-1","level":"INFO","level_value":20000,"trace_id":"1e38162b265be8c100ab58b1bf1c76bf","event.domain":"billing","trace_flags":"01","span_id":"bc70ff86eaa41fe3","log.category":"replay.success"}
{"@timestamp":"2026-01-07T09:25:22.4701995+05:30","@version":"1","message":"OUTPUT_STORED | file=ACC-UPSTATE-101_20260107092522_OUT.json | path=C:\\Users\\UMAR\\IdeaProjects\\billing-engine\\data\\success\\output\\ACC-UPSTATE-101_20260107092522_OUT.json | format=JSON","logger_name":"SUCCESS_LOG","thread_name":"http-nio-8080-exec-1","level":"INFO","level_value":20000,"trace_id":"c0518296c860faa6182410c1cb3ef573","event.domain":"billing","trace_flags":"01","span_id":"60bfb91f51293c40","log.category":"data.output"}
{"@timestamp":"2026-01-07T09:25:22.4777702+05:30","@version":"1","message":"PROCESSING_SUCCESS | account=ACC-UPSTATE-101 | totalDue=65.56","logger_name":"SUCCESS_LOG","thread_name":"http-nio-8080-exec-1","level":"INFO","level_value":20000,"trace_id":"c0518296c860faa6182410c1cb3ef573","event.domain":"billing","trace_flags":"01","span_id":"60bfb91f51293c40","log.category":"process.success"}
{"@timestamp":"2026-01-07T09:25:27.7213793+05:30","@version":"1","message":"OUTPUT_STORED | file=ACC-UPSTATE-101_20260107092527_OUT.json | path=C:\\Users\\UMAR\\IdeaProjects\\billing-engine\\data\\success\\output\\ACC-UPSTATE-101_20260107092527_OUT.json | format=JSON","logger_name":"SUCCESS_LOG","thread_name":"http-nio-8080-exec-3","level":"INFO","level_value":20000,"trace_id":"cb5285cab5d6c6fb75612cee8a8b747e","event.domain":"billing","trace_flags":"01","span_id":"49801d7a06ba9d07","log.category":"data.output"}
{"@timestamp":"2026-01-07T09:25:27.7263861+05:30","@version":"1","message":"PROCESSING_SUCCESS | account=ACC-UPSTATE-101 | totalDue=65.56","logger_name":"SUCCESS_LOG","thread_name":"http-nio-8080-exec-3","level":"INFO","level_value":20000,"trace_id":"cb5285cab5d6c6fb75612cee8a8b747e","event.domain":"billing","trace_flags":"01","span_id":"49801d7a06ba9d07","log.category":"process.success"}
{"@timestamp":"2026-01-07T09:25:29.1044917+05:30","@version":"1","message":"OUTPUT_STORED | file=ACC-UPSTATE-101_20260107092529_OUT.json | path=C:\\Users\\UMAR\\IdeaProjects\\billing-engine\\data\\success\\output\\ACC-UPSTATE-101_20260107092529_OUT.json | format=JSON","logger_name":"SUCCESS_LOG","thread_name":"http-nio-8080-exec-4","level":"INFO","level_value":20000,"trace_id":"173f362da99f3ee0c7e9f81324d8139b","event.domain":"billing","trace_flags":"01","span_id":"3f1e0fc60e7ad728","log.category":"data.output"}
{"@timestamp":"2026-01-07T09:25:29.1084883+05:30","@version":"1","message":"PROCESSING_SUCCESS | account=ACC-UPSTATE-101 | totalDue=65.56","logger_name":"SUCCESS_LOG","thread_name":"http-nio-8080-exec-4","level":"INFO","level_value":20000,"trace_id":"173f362da99f3ee0c7e9f81324d8139b","event.domain":"billing","trace_flags":"01","span_id":"3f1e0fc60e7ad728","log.category":"process.success"}
{"@timestamp":"2026-01-07T09:25:30.6747166+05:30","@version":"1","message":"OUTPUT_STORED | file=ACC-UPSTATE-101_20260107092530_OUT.json | path=C:\\Users\\UMAR\\IdeaProjects\\billing-engine\\data\\success\\output\\ACC-UPSTATE-101_20260107092530_OUT.json | format=JSON","logger_name":"SUCCESS_LOG","thread_name":"http-nio-8080-exec-5","level":"INFO","level_value":20000,"trace_id":"6bec613cf78271ab4db534e092ca574b","event.domain":"billing","trace_flags":"01","span_id":"d821f5312ab0722c","log.category":"data.output"}
{"@timestamp":"2026-01-07T09:25:30.6779852+05:30","@version":"1","message":"PROCESSING_SUCCESS | account=ACC-UPSTATE-101 | totalDue=65.56","logger_name":"SUCCESS_LOG","thread_name":"http-nio-8080-exec-5","level":"INFO","level_value":20000,"trace_id":"6bec613cf78271ab4db534e092ca574b","event.domain":"billing","trace_flags":"01","span_id":"d821f5312ab0722c","log.category":"process.success"}
{"@timestamp":"2026-01-07T09:26:03.8563362+05:30","@version":"1","message":"OUTPUT_STORED | file=ACC-UPSTATE-101_20260107092603_OUT.json | path=C:\\Users\\UMAR\\IdeaProjects\\billing-engine\\data\\success\\output\\ACC-UPSTATE-101_20260107092603_OUT.json | format=JSON","logger_name":"SUCCESS_LOG","thread_name":"http-nio-8080-exec-10","level":"INFO","level_value":20000,"trace_id":"3f96356ea1f93124b9b615dce96668a1","event.domain":"billing","trace_flags":"01","span_id":"06b52b8d931d723c","log.category":"data.output"}
{"@timestamp":"2026-01-07T09:26:03.8603365+05:30","@version":"1","message":"PROCESSING_SUCCESS | account=ACC-UPSTATE-101 | totalDue=65.56","logger_name":"SUCCESS_LOG","thread_name":"http-nio-8080-exec-10","level":"INFO","level_value":20000,"trace_id":"3f96356ea1f93124b9b615dce96668a1","event.domain":"billing","trace_flags":"01","span_id":"06b52b8d931d723c","log.category":"process.success"}
{"@timestamp":"2026-01-07T09:26:04.7030397+05:30","@version":"1","message":"OUTPUT_STORED | file=ACC-UPSTATE-101_20260107092604_OUT.json | path=C:\\Users\\UMAR\\IdeaProjects\\billing-engine\\data\\success\\output\\ACC-UPSTATE-101_20260107092604_OUT.json | format=JSON","logger_name":"SUCCESS_LOG","thread_name":"http-nio-8080-exec-2","level":"INFO","level_value":20000,"trace_id":"2957b2bbe5d8e59d6576c72e43f47961","event.domain":"billing","trace_flags":"01","span_id":"759296059538e12f","log.category":"data.output"}
{"@timestamp":"2026-01-07T09:26:04.7060419+05:30","@version":"1","message":"PROCESSING_SUCCESS | account=ACC-UPSTATE-101 | totalDue=65.56","logger_name":"SUCCESS_LOG","thread_name":"http-nio-8080-exec-2","level":"INFO","level_value":20000,"trace_id":"2957b2bbe5d8e59d6576c72e43f47961","event.domain":"billing","trace_flags":"01","span_id":"759296059538e12f","log.category":"process.success"}
{"@timestamp":"2026-01-07T09:26:05.4893488+05:30","@version":"1","message":"OUTPUT_STORED | file=ACC-UPSTATE-101_20260107092605_OUT.json | path=C:\\Users\\UMAR\\IdeaProjects\\billing-engine\\data\\success\\output\\ACC-UPSTATE-101_20260107092605_OUT.json | format=JSON","logger_name":"SUCCESS_LOG","thread_name":"http-nio-8080-exec-1","level":"INFO","level_value":20000,"trace_id":"098b3a2a96fb6b19949b8590510fd59c","event.domain":"billing","trace_flags":"01","span_id":"828800eee8353e34","log.category":"data.output"}
{"@timestamp":"2026-01-07T09:26:05.4943034+05:30","@version":"1","message":"PROCESSING_SUCCESS | account=ACC-UPSTATE-101 | totalDue=65.56","logger_name":"SUCCESS_LOG","thread_name":"http-nio-8080-exec-1","level":"INFO","level_value":20000,"trace_id":"098b3a2a96fb6b19949b8590510fd59c","event.domain":"billing","trace_flags":"01","span_id":"828800eee8353e34","log.category":"process.success"}
{"@timestamp":"2026-01-07T09:36:41.4666321+05:30","@version":"1","message":"OUTPUT_STORED | file=ACC777_20260107093641_OUT.xml | path=C:\\Users\\UMAR\\IdeaProjects\\billing-engine\\data\\success\\output\\ACC777_20260107093641_OUT.xml | format=XML","logger_name":"SUCCESS_LOG","thread_name":"main","level":"INFO","level_value":20000,"event.domain":"billing","log.category":"data.output"}
{"@timestamp":"2026-01-07T09:36:41.4730906+05:30","@version":"1","message":"PROCESSING_SUCCESS | account=ACC777 | totalDue=28.44","logger_name":"SUCCESS_LOG","thread_name":"main","level":"INFO","level_value":20000,"event.domain":"billing","log.category":"process.success"}
{"@timestamp":"2026-01-07T09:36:43.6332029+05:30","@version":"1","message":"OUTPUT_STORED | file=ACC999_OUT.xml | path=C:\\Users\\UMAR\\IdeaProjects\\billing-engine\\data\\success\\output\\ACC999_OUT.xml | format=XML","logger_name":"SUCCESS_LOG","thread_name":"main","level":"INFO","level_value":20000,"event.domain":"billing","log.category":"data.output"}
{"@timestamp":"2026-01-07T09:36:43.6382297+05:30","@version":"1","message":"REPLAY_SUCCESS | account=ACC999 | file=ACC999_20260107093643_IN.xml","logger_name":"SUCCESS_LOG","thread_name":"main","level":"INFO","level_value":20000,"event.domain":"billing","log.category":"replay.success"}
{"@timestamp":"2026-01-07T09:36:43.9483029+05:30","@version":"1","message":"OUTPUT_STORED | file=ACC123_20260107093643_OUT.json | path=C:\\Users\\UMAR\\IdeaProjects\\billing-engine\\data\\success\\output\\ACC123_20260107093643_OUT.json | format=JSON","logger_name":"SUCCESS_LOG","thread_name":"main","level":"INFO","level_value":20000,"event.domain":"billing","log.category":"data.output"}
{"@timestamp":"2026-01-07T09:36:43.9544104+05:30","@version":"1","message":"PROCESSING_SUCCESS | account=ACC123 | totalDue=36.40","logger_name":"SUCCESS_LOG","thread_name":"main","level":"INFO","level_value":20000,"event.domain":"billing","log.category":"process.success"}
{"@timestamp":"2026-01-07T09:49:50.6652471+05:30","@version":"1","message":"OUTPUT_STORED | file=ACC123_OUT.xml | path=C:\\Users\\UMAR\\IdeaProjects\\billing-engine\\data\\success\\output\\ACC123_OUT.xml | format=XML","logger_name":"SUCCESS_LOG","thread_name":"scheduling-1","level":"INFO","level_value":20000,"trace_id":"b4bb3767fdaa188f22db7322e71c3054","event.domain":"billing","trace_flags":"01","span_id":"2c1e838bbb751c8f","log.category":"data.output"}
{"@timestamp":"2026-01-07T09:49:50.6682348+05:30","@version":"1","message":"REPLAY_SUCCESS | account=ACC123 | file=ACC123_20260107093643_IN.xml","logger_name":"SUCCESS_LOG","thread_name":"scheduling-1","level":"INFO","level_value":20000,"trace_id":"b4bb3767fdaa188f22db7322e71c3054","event.domain":"billing","trace_flags":"01","span_id":"2c1e838bbb751c8f","log.category":"replay.success"}
{"@timestamp":"2026-01-07T10:38:14.3903654+05:30","@version":"1","message":"OUTPUT_STORED | file=ACC777_20260107103814_OUT.xml | path=C:\\Users\\UMAR\\IdeaProjects\\billing-engine\\data\\success\\output\\ACC777_20260107103814_OUT.xml | format=XML","logger_name":"SUCCESS_LOG","thread_name":"main","level":"INFO","level_value":20000,"event.domain":"billing","log.category":"data.output"}
{"@timestamp":"2026-01-07T10:38:14.3923801+05:30","@version":"1","message":"PROCESSING_SUCCESS | account=ACC777 | totalDue=28.44","logger_name":"SUCCESS_LOG","thread_name":"main","level":"INFO","level_value":20000,"event.domain":"billing","log.category":"process.success"}
{"@timestamp":"2026-01-07T10:38:15.2696002+05:30","@version":"1","message":"OUTPUT_STORED | file=ACC999_OUT.xml | path=C:\\Users\\UMAR\\IdeaProjects\\billing-engine\\data\\success\\output\\ACC999_OUT.xml | format=XML","logger_name":"SUCCESS_LOG","thread_name":"main","level":"INFO","level_value":20000,"event.domain":"billing","log.category":"data.output"}
{"@timestamp":"2026-01-07T10:38:15.2717587+05:30","@version":"1","message":"REPLAY_SUCCESS | account=ACC999 | file=ACC999_20260107103815_IN.xml","logger_name":"SUCCESS_LOG","thread_name":"main","level":"INFO","level_value":20000,"event.domain":"billing","log.category":"replay.success"}
{"@timestamp":"2026-01-07T10:38:15.3917541+05:30","@version":"1","message":"OUTPUT_STORED | file=ACC123_20260107103815_OUT.json | path=C:\\Users\\UMAR\\IdeaProjects\\billing-engine\\data\\success\\output\\ACC123_20260107103815_OUT.json | format=JSON","logger_name":"SUCCESS_LOG","thread_name":"main","level":"INFO","level_value":20000,"event.domain":"billing","log.category":"data.output"}
{"@timestamp":"2026-01-07T10:38:15.3946254+05:30","@version":"1","message":"PROCESSING_SUCCESS | account=ACC123 | totalDue=36.40","logger_name":"SUCCESS_LOG","thread_name":"main","level":"INFO","level_value":20000,"event.domain":"billing","log.category":"process.success"}
